{
  "station": "El Masnou NE",
  "generated_at_utc": "2026-04-23T10:53:12.852445+00:00",
  "matched_model_time": "2026-04-23T11:00",
  "observed_time_utc": "2026,4,23,10,53,4",
  "real": {
    "temperature_c": 19.9,
    "humidity_pct": 55,
    "pressure_hpa": 1022.8,
    "wind_speed_kmh": 10.0,
    "wind_gust_kmh": 24.0,
    "dominant_wind_dir": "E",
    "rain_today_mm": 0.0
  },
  "forecast": {
    "temperature_c": 20.1,
    "humidity_pct": 44,
    "pressure_hpa": 1021.3,
    "wind_speed_kmh": 32.7
  },
  "deviation": {
    "temperature_c": -0.2,
    "humidity_pct": 11,
    "pressure_hpa": 1.5,
    "wind_speed_kmh": -22.7
  },
  "learning": {
    "bias_temperature_c": {
      "h6": -0.46,
      "h12": -0.5,
      "h24": -0.65
    },
    "samples": {
      "h6": 30,
      "h12": 30,
      "h24": 30
    }
  },
  "quality": {
    "temperature": "baja",
    "humidity": "media",
    "pressure": "baja",
    "wind": "alta"
  }
}