{
  "station": "El Masnou NE",
  "generated_at_utc": "2026-04-14T07:53:12.824635+00:00",
  "matched_model_time": "2026-04-14T08:00",
  "observed_time_utc": "2026,4,14,7,52,53",
  "real": {
    "temperature_c": 14.4,
    "humidity_pct": 64,
    "pressure_hpa": 1017.0,
    "wind_speed_kmh": 8.0,
    "wind_gust_kmh": 18.0,
    "dominant_wind_dir": "NW",
    "rain_today_mm": 0.3
  },
  "forecast": {
    "temperature_c": 13.5,
    "humidity_pct": 74,
    "pressure_hpa": 1016.4,
    "wind_speed_kmh": 6.9
  },
  "deviation": {
    "temperature_c": 0.9,
    "humidity_pct": -10,
    "pressure_hpa": 0.6,
    "wind_speed_kmh": 1.1
  },
  "learning": {
    "bias_temperature_c": {
      "h6": -0.15,
      "h12": -0.4,
      "h24": -0.11
    },
    "samples": {
      "h6": 30,
      "h12": 30,
      "h24": 30
    }
  },
  "quality": {
    "temperature": "media",
    "humidity": "media",
    "pressure": "baja",
    "wind": "baja"
  }
}