{
  "station": "El Masnou NE",
  "generated_at_utc": "2026-04-03T05:33:12.779318+00:00",
  "matched_model_time": "2026-04-03T06:00",
  "observed_time_utc": "2026,4,3,5,33,10",
  "real": {
    "temperature_c": 11.7,
    "humidity_pct": 64,
    "pressure_hpa": 1018.0,
    "wind_speed_kmh": 3.0,
    "wind_gust_kmh": 5.0,
    "dominant_wind_dir": "WSW",
    "rain_today_mm": 0.0
  },
  "forecast": {
    "temperature_c": 7.0,
    "humidity_pct": 79,
    "pressure_hpa": 1017.9,
    "wind_speed_kmh": 8.6
  },
  "deviation": {
    "temperature_c": 4.7,
    "humidity_pct": -15,
    "pressure_hpa": 0.1,
    "wind_speed_kmh": -5.6
  },
  "learning": {
    "bias_temperature_c": {
      "h6": 1.11,
      "h12": 1.26,
      "h24": 1.25
    },
    "samples": {
      "h6": 30,
      "h12": 30,
      "h24": 30
    }
  },
  "quality": {
    "temperature": "alta",
    "humidity": "alta",
    "pressure": "baja",
    "wind": "media"
  }
}