{
  "station": "El Masnou NE",
  "generated_at_utc": "2026-07-18T03:13:13.139744+00:00",
  "matched_model_time": "2026-07-18T03:00",
  "observed_time_utc": "2026,7,18,3,12,42",
  "real": {
    "temperature_c": 25.8,
    "humidity_pct": 91,
    "pressure_hpa": 1016.4,
    "wind_speed_kmh": 0.0,
    "wind_gust_kmh": 0.0,
    "dominant_wind_dir": "SSW",
    "rain_today_mm": 0.0
  },
  "forecast": {
    "temperature_c": 23.6,
    "humidity_pct": 91,
    "pressure_hpa": 1014.7,
    "wind_speed_kmh": 5.1
  },
  "deviation": {
    "temperature_c": 2.2,
    "humidity_pct": 0,
    "pressure_hpa": 1.7,
    "wind_speed_kmh": -5.1
  },
  "learning": {
    "bias_temperature_c": {
      "h6": 0.38,
      "h12": 0.39,
      "h24": 0.24
    },
    "samples": {
      "h6": 30,
      "h12": 30,
      "h24": 30
    }
  },
  "quality": {
    "temperature": "alta",
    "humidity": "baja",
    "pressure": "media",
    "wind": "media"
  }
}