{
  "station": "El Masnou NE",
  "generated_at_utc": "2026-04-03T00:53:12.031425+00:00",
  "source_file": "C:\\CumulusMX\\web\\realtimegauges.txt",
  "observation_time_utc": "2026,4,3,0,53,8",
  "forecast_text": "Settled fine",
  "sensor_contact_lost": 0,
  "temperature_c": 12.1,
  "dewpoint_c": 3.1,
  "apparent_temperature_c": 10.5,
  "feels_like_c": 11.9,
  "humidity_pct": 54,
  "pressure_hpa": 1016.6,
  "pressure_trend_hpa": 0.0,
  "rain_today_mm": 0.0,
  "rain_rate_mm_h": 0.0,
  "last_rain_tip_iso": "2026-03-29 01:24",
  "wind_latest_kmh": 0.0,
  "wind_speed_kmh": 1.0,
  "wind_gust_kmh": 5.0,
  "wind_gust_daymax_kmh": 24.0,
  "wind_bearing_deg": 7,
  "wind_avg_bearing_deg": 29,
  "dominant_wind_dir": "SW",
  "wind_run_km": 89.7,
  "uv_index": 0.0,
  "solar_radiation_w_m2": 0.0,
  "cloudbase_ft": 3681.0,
  "units": {
    "temperature": "C",
    "wind": "km/h",
    "pressure": "hPa",
    "rain": "mm",
    "cloudbase": "ft"
  },
  "meta": {
    "cumulus_version": "4.7.0",
    "cumulus_build": "4137",
    "format_version": "12"
  }
}