{
  "station": "El Masnou NE",
  "generated_at_utc": "2026-04-01T21:13:11.983720+00:00",
  "source_file": "C:\\CumulusMX\\web\\realtimegauges.txt",
  "observation_time_utc": "2026,4,1,21,13,7",
  "forecast_text": "Fine weather",
  "sensor_contact_lost": 0,
  "temperature_c": 13.4,
  "dewpoint_c": 10.7,
  "apparent_temperature_c": 12.8,
  "feels_like_c": 13.3,
  "humidity_pct": 84,
  "pressure_hpa": 1015.6,
  "pressure_trend_hpa": 0.3,
  "rain_today_mm": 0.0,
  "rain_rate_mm_h": 0.0,
  "last_rain_tip_iso": "2026-03-29 01:24",
  "wind_latest_kmh": 5.0,
  "wind_speed_kmh": 4.0,
  "wind_gust_kmh": 9.0,
  "wind_gust_daymax_kmh": 20.0,
  "wind_bearing_deg": 245,
  "wind_avg_bearing_deg": 231,
  "dominant_wind_dir": "WSW",
  "wind_run_km": 81.5,
  "uv_index": 0.0,
  "solar_radiation_w_m2": 0.0,
  "cloudbase_ft": 1104.0,
  "units": {
    "temperature": "C",
    "wind": "km/h",
    "pressure": "hPa",
    "rain": "mm",
    "cloudbase": "ft"
  },
  "meta": {
    "cumulus_version": "4.7.0",
    "cumulus_build": "4137",
    "format_version": "12"
  }
}