{"cod":"200","message":0,"cnt":40,"list":[{"dt":1776945600,"main":{"temp":18.8,"feels_like":18.17,"temp_min":18.8,"temp_max":19.71,"pressure":1021,"sea_level":1021,"grnd_level":1012,"humidity":55,"temp_kf":-0.91},"weather":[{"id":801,"main":"Clouds","description":"lleugerament ennuvolat","icon":"02d"}],"clouds":{"all":21},"wind":{"speed":8.2,"deg":86,"gust":9.86},"visibility":10000,"pop":0,"sys":{"pod":"d"},"dt_txt":"2026-04-23 12:00:00"},{"dt":1776956400,"main":{"temp":18.84,"feels_like":18.22,"temp_min":18.84,"temp_max":19.09,"pressure":1020,"sea_level":1020,"grnd_level":1012,"humidity":55,"temp_kf":-0.25},"weather":[{"id":800,"main":"Clear","description":"cel net","icon":"01d"}],"clouds":{"all":10},"wind":{"speed":8.28,"deg":90,"gust":10.22},"visibility":10000,"pop":0,"sys":{"pod":"d"},"dt_txt":"2026-04-23 15:00:00"},{"dt":1776967200,"main":{"temp":16.61,"feels_like":15.81,"temp_min":16.61,"temp_max":16.61,"pressure":1020,"sea_level":1020,"grnd_level":1012,"humidity":57,"temp_kf":0},"weather":[{"id":801,"main":"Clouds","description":"lleugerament ennuvolat","icon":"02d"}],"clouds":{"all":24},"wind":{"speed":7.31,"deg":71,"gust":10.76},"visibility":10000,"pop":0,"sys":{"pod":"d"},"dt_txt":"2026-04-23 18:00:00"},{"dt":1776978000,"main":{"temp":15.55,"feels_like":14.57,"temp_min":15.55,"temp_max":15.55,"pressure":1021,"sea_level":1021,"grnd_level":1013,"humidity":54,"temp_kf":0},"weather":[{"id":804,"main":"Clouds","description":"ennuvolat","icon":"04n"}],"clouds":{"all":90},"wind":{"speed":5.15,"deg":55,"gust":9.03},"visibility":10000,"pop":0,"sys":{"pod":"n"},"dt_txt":"2026-04-23 21:00:00"},{"dt":1776988800,"main":{"temp":14.16,"feels_like":13.09,"temp_min":14.16,"temp_max":14.16,"pressure":1020,"sea_level":1020,"grnd_level":1012,"humidity":56,"temp_kf":0},"weather":[{"id":804,"main":"Clouds","description":"ennuvolat","icon":"04n"}],"clouds":{"all":88},"wind":{"speed":3.9,"deg":50,"gust":5.75},"visibility":10000,"pop":0,"sys":{"pod":"n"},"dt_txt":"2026-04-24 00:00:00"},{"dt":1776999600,"main":{"temp":15.24,"feels_like":14.41,"temp_min":15.24,"temp_max":15.24,"pressure":1020,"sea_level":1020,"grnd_level":1012,"humidity":61,"temp_kf":0},"weather":[{"id":804,"main":"Clouds","description":"ennuvolat","icon":"04n"}],"clouds":{"all":95},"wind":{"speed":2.53,"deg":53,"gust":2.89},"visibility":10000,"pop":0,"sys":{"pod":"n"},"dt_txt":"2026-04-24 03:00:00"},{"dt":1777010400,"main":{"temp":15.05,"feels_like":14.2,"temp_min":15.05,"temp_max":15.05,"pressure":1020,"sea_level":1020,"grnd_level":1012,"humidity":61,"temp_kf":0},"weather":[{"id":803,"main":"Clouds","description":"nuvolositat variable","icon":"04d"}],"clouds":{"all":64},"wind":{"speed":1.64,"deg":38,"gust":1.62},"visibility":10000,"pop":0,"sys":{"pod":"d"},"dt_txt":"2026-04-24 06:00:00"},{"dt":1777021200,"main":{"temp":17.59,"feels_like":16.71,"temp_min":17.59,"temp_max":17.59,"pressure":1020,"sea_level":1020,"grnd_level":1012,"humidity":50,"temp_kf":0},"weather":[{"id":801,"main":"Clouds","description":"lleugerament ennuvolat","icon":"02d"}],"clouds":{"all":13},"wind":{"speed":2.58,"deg":124,"gust":2.35},"visibility":10000,"pop":0,"sys":{"pod":"d"},"dt_txt":"2026-04-24 09:00:00"},{"dt":1777032000,"main":{"temp":17.71,"feels_like":16.92,"temp_min":17.71,"temp_max":17.71,"pressure":1020,"sea_level":1020,"grnd_level":1012,"humidity":53,"temp_kf":0},"weather":[{"id":802,"main":"Clouds","description":"núvols dispersos","icon":"03d"}],"clouds":{"all":47},"wind":{"speed":3.73,"deg":137,"gust":3.89},"visibility":10000,"pop":0,"sys":{"pod":"d"},"dt_txt":"2026-04-24 12:00:00"},{"dt":1777042800,"main":{"temp":17.53,"feels_like":16.67,"temp_min":17.53,"temp_max":17.53,"pressure":1019,"sea_level":1019,"grnd_level":1011,"humidity":51,"temp_kf":0},"weather":[{"id":804,"main":"Clouds","description":"ennuvolat","icon":"04d"}],"clouds":{"all":100},"wind":{"speed":2.83,"deg":131,"gust":2.96},"visibility":10000,"pop":0,"sys":{"pod":"d"},"dt_txt":"2026-04-24 15:00:00"},{"dt":1777053600,"main":{"temp":16.53,"feels_like":15.78,"temp_min":16.53,"temp_max":16.53,"pressure":1018,"sea_level":1018,"grnd_level":1010,"humidity":59,"temp_kf":0},"weather":[{"id":804,"main":"Clouds","description":"ennuvolat","icon":"04d"}],"clouds":{"all":100},"wind":{"speed":1.2,"deg":149,"gust":1.2},"visibility":10000,"pop":0,"sys":{"pod":"d"},"dt_txt":"2026-04-24 18:00:00"},{"dt":1777064400,"main":{"temp":15.77,"feels_like":15.2,"temp_min":15.77,"temp_max":15.77,"pressure":1019,"sea_level":1019,"grnd_level":1011,"humidity":69,"temp_kf":0},"weather":[{"id":804,"main":"Clouds","description":"ennuvolat","icon":"04n"}],"clouds":{"all":98},"wind":{"speed":0.41,"deg":101,"gust":0.24},"visibility":10000,"pop":0,"sys":{"pod":"n"},"dt_txt":"2026-04-24 21:00:00"},{"dt":1777075200,"main":{"temp":15.18,"feels_like":14.69,"temp_min":15.18,"temp_max":15.18,"pressure":1018,"sea_level":1018,"grnd_level":1010,"humidity":74,"temp_kf":0},"weather":[{"id":803,"main":"Clouds","description":"nuvolositat variable","icon":"04n"}],"clouds":{"all":82},"wind":{"speed":0.94,"deg":156,"gust":0.98},"visibility":10000,"pop":0,"sys":{"pod":"n"},"dt_txt":"2026-04-25 00:00:00"},{"dt":1777086000,"main":{"temp":14.53,"feels_like":14.08,"temp_min":14.53,"temp_max":14.53,"pressure":1018,"sea_level":1018,"grnd_level":1010,"humidity":78,"temp_kf":0},"weather":[{"id":803,"main":"Clouds","description":"nuvolositat variable","icon":"04n"}],"clouds":{"all":59},"wind":{"speed":1.29,"deg":21,"gust":1.31},"visibility":10000,"pop":0,"sys":{"pod":"n"},"dt_txt":"2026-04-25 03:00:00"},{"dt":1777096800,"main":{"temp":14.78,"feels_like":13.98,"temp_min":14.78,"temp_max":14.78,"pressure":1018,"sea_level":1018,"grnd_level":1010,"humidity":64,"temp_kf":0},"weather":[{"id":803,"main":"Clouds","description":"nuvolositat variable","icon":"04d"}],"clouds":{"all":78},"wind":{"speed":1.2,"deg":24,"gust":1.18},"visibility":10000,"pop":0,"sys":{"pod":"d"},"dt_txt":"2026-04-25 06:00:00"},{"dt":1777107600,"main":{"temp":17.29,"feels_like":16.54,"temp_min":17.29,"temp_max":17.29,"pressure":1019,"sea_level":1019,"grnd_level":1011,"humidity":56,"temp_kf":0},"weather":[{"id":803,"main":"Clouds","description":"nuvolositat variable","icon":"04d"}],"clouds":{"all":83},"wind":{"speed":2.34,"deg":151,"gust":1.8},"visibility":10000,"pop":0,"sys":{"pod":"d"},"dt_txt":"2026-04-25 09:00:00"},{"dt":1777118400,"main":{"temp":18.28,"feels_like":17.68,"temp_min":18.28,"temp_max":18.28,"pressure":1018,"sea_level":1018,"grnd_level":1010,"humidity":58,"temp_kf":0},"weather":[{"id":803,"main":"Clouds","description":"nuvolositat variable","icon":"04d"}],"clouds":{"all":59},"wind":{"speed":2.54,"deg":150,"gust":2},"visibility":10000,"pop":0,"sys":{"pod":"d"},"dt_txt":"2026-04-25 12:00:00"},{"dt":1777129200,"main":{"temp":17.7,"feels_like":16.99,"temp_min":17.7,"temp_max":17.7,"pressure":1018,"sea_level":1018,"grnd_level":1010,"humidity":56,"temp_kf":0},"weather":[{"id":803,"main":"Clouds","description":"nuvolositat variable","icon":"04d"}],"clouds":{"all":82},"wind":{"speed":3.16,"deg":170,"gust":3.28},"visibility":10000,"pop":0,"sys":{"pod":"d"},"dt_txt":"2026-04-25 15:00:00"},{"dt":1777140000,"main":{"temp":17.48,"feels_like":16.67,"temp_min":17.48,"temp_max":17.48,"pressure":1018,"sea_level":1018,"grnd_level":1010,"humidity":53,"temp_kf":0},"weather":[{"id":804,"main":"Clouds","description":"ennuvolat","icon":"04d"}],"clouds":{"all":95},"wind":{"speed":0.98,"deg":171,"gust":0.87},"visibility":10000,"pop":0,"sys":{"pod":"d"},"dt_txt":"2026-04-25 18:00:00"},{"dt":1777150800,"main":{"temp":16.48,"feels_like":15.72,"temp_min":16.48,"temp_max":16.48,"pressure":1019,"sea_level":1019,"grnd_level":1011,"humidity":59,"temp_kf":0},"weather":[{"id":802,"main":"Clouds","description":"núvols dispersos","icon":"03n"}],"clouds":{"all":48},"wind":{"speed":2.31,"deg":230,"gust":3.06},"visibility":10000,"pop":0,"sys":{"pod":"n"},"dt_txt":"2026-04-25 21:00:00"},{"dt":1777161600,"main":{"temp":16.25,"feels_like":15.42,"temp_min":16.25,"temp_max":16.25,"pressure":1018,"sea_level":1018,"grnd_level":1010,"humidity":57,"temp_kf":0},"weather":[{"id":802,"main":"Clouds","description":"núvols dispersos","icon":"03n"}],"clouds":{"all":37},"wind":{"speed":2.26,"deg":228,"gust":2.23},"visibility":10000,"pop":0,"sys":{"pod":"n"},"dt_txt":"2026-04-26 00:00:00"},{"dt":1777172400,"main":{"temp":16.03,"feels_like":15.15,"temp_min":16.03,"temp_max":16.03,"pressure":1018,"sea_level":1018,"grnd_level":1010,"humidity":56,"temp_kf":0},"weather":[{"id":803,"main":"Clouds","description":"nuvolositat variable","icon":"04n"}],"clouds":{"all":62},"wind":{"speed":1.11,"deg":267,"gust":1.27},"visibility":10000,"pop":0,"sys":{"pod":"n"},"dt_txt":"2026-04-26 03:00:00"},{"dt":1777183200,"main":{"temp":16.59,"feels_like":15.87,"temp_min":16.59,"temp_max":16.59,"pressure":1018,"sea_level":1018,"grnd_level":1010,"humidity":60,"temp_kf":0},"weather":[{"id":802,"main":"Clouds","description":"núvols dispersos","icon":"03d"}],"clouds":{"all":39},"wind":{"speed":0.87,"deg":345,"gust":0.79},"visibility":10000,"pop":0,"sys":{"pod":"d"},"dt_txt":"2026-04-26 06:00:00"},{"dt":1777194000,"main":{"temp":19.42,"feels_like":18.64,"temp_min":19.42,"temp_max":19.42,"pressure":1020,"sea_level":1020,"grnd_level":1012,"humidity":47,"temp_kf":0},"weather":[{"id":803,"main":"Clouds","description":"nuvolositat variable","icon":"04d"}],"clouds":{"all":53},"wind":{"speed":2.9,"deg":192,"gust":2.66},"visibility":10000,"pop":0,"sys":{"pod":"d"},"dt_txt":"2026-04-26 09:00:00"},{"dt":1777204800,"main":{"temp":20.19,"feels_like":19.44,"temp_min":20.19,"temp_max":20.19,"pressure":1019,"sea_level":1019,"grnd_level":1011,"humidity":45,"temp_kf":0},"weather":[{"id":803,"main":"Clouds","description":"nuvolositat variable","icon":"04d"}],"clouds":{"all":73},"wind":{"speed":3.39,"deg":190,"gust":3.33},"visibility":10000,"pop":0,"sys":{"pod":"d"},"dt_txt":"2026-04-26 12:00:00"},{"dt":1777215600,"main":{"temp":20.08,"feels_like":19.45,"temp_min":20.08,"temp_max":20.08,"pressure":1018,"sea_level":1018,"grnd_level":1010,"humidity":50,"temp_kf":0},"weather":[{"id":802,"main":"Clouds","description":"núvols dispersos","icon":"03d"}],"clouds":{"all":40},"wind":{"speed":4.01,"deg":194,"gust":4.17},"visibility":10000,"pop":0,"sys":{"pod":"d"},"dt_txt":"2026-04-26 15:00:00"},{"dt":1777226400,"main":{"temp":18.78,"feels_like":18.18,"temp_min":18.78,"temp_max":18.78,"pressure":1019,"sea_level":1019,"grnd_level":1011,"humidity":56,"temp_kf":0},"weather":[{"id":801,"main":"Clouds","description":"lleugerament ennuvolat","icon":"02d"}],"clouds":{"all":19},"wind":{"speed":3.05,"deg":211,"gust":4.15},"visibility":10000,"pop":0,"sys":{"pod":"d"},"dt_txt":"2026-04-26 18:00:00"},{"dt":1777237200,"main":{"temp":18.18,"feels_like":17.54,"temp_min":18.18,"temp_max":18.18,"pressure":1020,"sea_level":1020,"grnd_level":1012,"humidity":57,"temp_kf":0},"weather":[{"id":800,"main":"Clear","description":"cel net","icon":"01n"}],"clouds":{"all":0},"wind":{"speed":1.3,"deg":261,"gust":1.47},"visibility":10000,"pop":0,"sys":{"pod":"n"},"dt_txt":"2026-04-26 21:00:00"},{"dt":1777248000,"main":{"temp":17.99,"feels_like":17.33,"temp_min":17.99,"temp_max":17.99,"pressure":1019,"sea_level":1019,"grnd_level":1011,"humidity":57,"temp_kf":0},"weather":[{"id":800,"main":"Clear","description":"cel net","icon":"01n"}],"clouds":{"all":2},"wind":{"speed":1.98,"deg":254,"gust":2.05},"visibility":10000,"pop":0,"sys":{"pod":"n"},"dt_txt":"2026-04-27 00:00:00"},{"dt":1777258800,"main":{"temp":17.76,"feels_like":17.16,"temp_min":17.76,"temp_max":17.76,"pressure":1018,"sea_level":1018,"grnd_level":1010,"humidity":60,"temp_kf":0},"weather":[{"id":802,"main":"Clouds","description":"núvols dispersos","icon":"03n"}],"clouds":{"all":31},"wind":{"speed":0.35,"deg":278,"gust":0.9},"visibility":10000,"pop":0,"sys":{"pod":"n"},"dt_txt":"2026-04-27 03:00:00"},{"dt":1777269600,"main":{"temp":17.45,"feels_like":16.84,"temp_min":17.45,"temp_max":17.45,"pressure":1018,"sea_level":1018,"grnd_level":1010,"humidity":61,"temp_kf":0},"weather":[{"id":802,"main":"Clouds","description":"núvols dispersos","icon":"03d"}],"clouds":{"all":41},"wind":{"speed":0.33,"deg":81,"gust":0.91},"visibility":10000,"pop":0,"sys":{"pod":"d"},"dt_txt":"2026-04-27 06:00:00"},{"dt":1777280400,"main":{"temp":19.37,"feels_like":18.77,"temp_min":19.37,"temp_max":19.37,"pressure":1019,"sea_level":1019,"grnd_level":1011,"humidity":54,"temp_kf":0},"weather":[{"id":802,"main":"Clouds","description":"núvols dispersos","icon":"03d"}],"clouds":{"all":35},"wind":{"speed":1.65,"deg":165,"gust":1.14},"visibility":10000,"pop":0,"sys":{"pod":"d"},"dt_txt":"2026-04-27 09:00:00"},{"dt":1777291200,"main":{"temp":18.87,"feels_like":18.22,"temp_min":18.87,"temp_max":18.87,"pressure":1018,"sea_level":1018,"grnd_level":1010,"humidity":54,"temp_kf":0},"weather":[{"id":803,"main":"Clouds","description":"nuvolositat variable","icon":"04d"}],"clouds":{"all":62},"wind":{"speed":2.01,"deg":178,"gust":2.03},"visibility":10000,"pop":0,"sys":{"pod":"d"},"dt_txt":"2026-04-27 12:00:00"},{"dt":1777302000,"main":{"temp":20.29,"feels_like":19.76,"temp_min":20.29,"temp_max":20.29,"pressure":1016,"sea_level":1016,"grnd_level":1009,"humidity":53,"temp_kf":0},"weather":[{"id":802,"main":"Clouds","description":"núvols dispersos","icon":"03d"}],"clouds":{"all":26},"wind":{"speed":3.4,"deg":183,"gust":3.7},"visibility":10000,"pop":0,"sys":{"pod":"d"},"dt_txt":"2026-04-27 15:00:00"},{"dt":1777312800,"main":{"temp":19.21,"feels_like":18.78,"temp_min":19.21,"temp_max":19.21,"pressure":1016,"sea_level":1016,"grnd_level":1009,"humidity":61,"temp_kf":0},"weather":[{"id":803,"main":"Clouds","description":"nuvolositat variable","icon":"04d"}],"clouds":{"all":58},"wind":{"speed":2.14,"deg":211,"gust":3.02},"visibility":10000,"pop":0,"sys":{"pod":"d"},"dt_txt":"2026-04-27 18:00:00"},{"dt":1777323600,"main":{"temp":18.02,"feels_like":17.57,"temp_min":18.02,"temp_max":18.02,"pressure":1017,"sea_level":1017,"grnd_level":1009,"humidity":65,"temp_kf":0},"weather":[{"id":802,"main":"Clouds","description":"núvols dispersos","icon":"03n"}],"clouds":{"all":42},"wind":{"speed":0.75,"deg":235,"gust":1.12},"visibility":10000,"pop":0,"sys":{"pod":"n"},"dt_txt":"2026-04-27 21:00:00"},{"dt":1777334400,"main":{"temp":17.76,"feels_like":17.29,"temp_min":17.76,"temp_max":17.76,"pressure":1016,"sea_level":1016,"grnd_level":1008,"humidity":65,"temp_kf":0},"weather":[{"id":803,"main":"Clouds","description":"nuvolositat variable","icon":"04n"}],"clouds":{"all":71},"wind":{"speed":1.6,"deg":250,"gust":1.56},"visibility":10000,"pop":0,"sys":{"pod":"n"},"dt_txt":"2026-04-28 00:00:00"},{"dt":1777345200,"main":{"temp":17.47,"feels_like":16.94,"temp_min":17.47,"temp_max":17.47,"pressure":1015,"sea_level":1015,"grnd_level":1007,"humidity":64,"temp_kf":0},"weather":[{"id":804,"main":"Clouds","description":"ennuvolat","icon":"04n"}],"clouds":{"all":97},"wind":{"speed":1.38,"deg":271,"gust":1.47},"visibility":10000,"pop":0,"sys":{"pod":"n"},"dt_txt":"2026-04-28 03:00:00"},{"dt":1777356000,"main":{"temp":17.28,"feels_like":16.71,"temp_min":17.28,"temp_max":17.28,"pressure":1015,"sea_level":1015,"grnd_level":1007,"humidity":63,"temp_kf":0},"weather":[{"id":803,"main":"Clouds","description":"nuvolositat variable","icon":"04d"}],"clouds":{"all":70},"wind":{"speed":0.9,"deg":291,"gust":1.07},"visibility":10000,"pop":0,"sys":{"pod":"d"},"dt_txt":"2026-04-28 06:00:00"},{"dt":1777366800,"main":{"temp":20.31,"feels_like":19.73,"temp_min":20.31,"temp_max":20.31,"pressure":1015,"sea_level":1015,"grnd_level":1007,"humidity":51,"temp_kf":0},"weather":[{"id":800,"main":"Clear","description":"cel net","icon":"01d"}],"clouds":{"all":5},"wind":{"speed":2.27,"deg":181,"gust":1.84},"visibility":10000,"pop":0,"sys":{"pod":"d"},"dt_txt":"2026-04-28 09:00:00"}],"city":{"id":6356147,"name":"Masnou, El","coord":{"lat":41.4853,"lon":2.3275},"country":"ES","population":22288,"timezone":7200,"sunrise":1776920339,"sunset":1776969524}}