{"cod":"200","message":0,"cnt":40,"list":[{"dt":1772442000,"main":{"temp":12.1,"feels_like":11.53,"temp_min":11.1,"temp_max":12.1,"pressure":1021,"sea_level":1021,"grnd_level":1013,"humidity":83,"temp_kf":1},"weather":[{"id":800,"main":"Clear","description":"cel net","icon":"01d"}],"clouds":{"all":9},"wind":{"speed":0.64,"deg":182,"gust":1.2},"visibility":10000,"pop":0,"sys":{"pod":"d"},"dt_txt":"2026-03-02 09:00:00"},{"dt":1772452800,"main":{"temp":12.81,"feels_like":12.24,"temp_min":12.81,"temp_max":14.23,"pressure":1021,"sea_level":1021,"grnd_level":1013,"humidity":80,"temp_kf":-1.42},"weather":[{"id":801,"main":"Clouds","description":"lleugerament ennuvolat","icon":"02d"}],"clouds":{"all":12},"wind":{"speed":2.45,"deg":155,"gust":2.68},"visibility":10000,"pop":0,"sys":{"pod":"d"},"dt_txt":"2026-03-02 12:00:00"},{"dt":1772463600,"main":{"temp":13.43,"feels_like":12.76,"temp_min":13.43,"temp_max":14.1,"pressure":1020,"sea_level":1020,"grnd_level":1012,"humidity":74,"temp_kf":-0.67},"weather":[{"id":802,"main":"Clouds","description":"núvols dispersos","icon":"03d"}],"clouds":{"all":48},"wind":{"speed":2.76,"deg":146,"gust":2.46},"visibility":10000,"pop":0,"sys":{"pod":"d"},"dt_txt":"2026-03-02 15:00:00"},{"dt":1772474400,"main":{"temp":12.78,"feels_like":12.23,"temp_min":12.78,"temp_max":12.78,"pressure":1020,"sea_level":1020,"grnd_level":1012,"humidity":81,"temp_kf":0},"weather":[{"id":802,"main":"Clouds","description":"núvols dispersos","icon":"03n"}],"clouds":{"all":47},"wind":{"speed":2.22,"deg":80,"gust":2.35},"visibility":10000,"pop":0,"sys":{"pod":"n"},"dt_txt":"2026-03-02 18:00:00"},{"dt":1772485200,"main":{"temp":12.43,"feels_like":11.95,"temp_min":12.43,"temp_max":12.43,"pressure":1021,"sea_level":1021,"grnd_level":1013,"humidity":85,"temp_kf":0},"weather":[{"id":804,"main":"Clouds","description":"ennuvolat","icon":"04n"}],"clouds":{"all":100},"wind":{"speed":3.13,"deg":44,"gust":3.89},"visibility":10000,"pop":0,"sys":{"pod":"n"},"dt_txt":"2026-03-02 21:00:00"},{"dt":1772496000,"main":{"temp":12.23,"feels_like":11.62,"temp_min":12.23,"temp_max":12.23,"pressure":1022,"sea_level":1022,"grnd_level":1013,"humidity":81,"temp_kf":0},"weather":[{"id":804,"main":"Clouds","description":"ennuvolat","icon":"04n"}],"clouds":{"all":95},"wind":{"speed":3.67,"deg":31,"gust":4.84},"visibility":10000,"pop":0,"sys":{"pod":"n"},"dt_txt":"2026-03-03 00:00:00"},{"dt":1772506800,"main":{"temp":11.53,"feels_like":10.75,"temp_min":11.53,"temp_max":11.53,"pressure":1021,"sea_level":1021,"grnd_level":1013,"humidity":77,"temp_kf":0},"weather":[{"id":804,"main":"Clouds","description":"ennuvolat","icon":"04n"}],"clouds":{"all":100},"wind":{"speed":3.35,"deg":32,"gust":4.64},"visibility":10000,"pop":0,"sys":{"pod":"n"},"dt_txt":"2026-03-03 03:00:00"},{"dt":1772517600,"main":{"temp":11.83,"feels_like":11.11,"temp_min":11.83,"temp_max":11.83,"pressure":1021,"sea_level":1021,"grnd_level":1013,"humidity":78,"temp_kf":0},"weather":[{"id":804,"main":"Clouds","description":"ennuvolat","icon":"04n"}],"clouds":{"all":100},"wind":{"speed":4.16,"deg":35,"gust":6.82},"visibility":10000,"pop":0,"sys":{"pod":"n"},"dt_txt":"2026-03-03 06:00:00"},{"dt":1772528400,"main":{"temp":14.55,"feels_like":13.94,"temp_min":14.55,"temp_max":14.55,"pressure":1021,"sea_level":1021,"grnd_level":1013,"humidity":72,"temp_kf":0},"weather":[{"id":804,"main":"Clouds","description":"ennuvolat","icon":"04d"}],"clouds":{"all":97},"wind":{"speed":6.18,"deg":51,"gust":11.65},"visibility":10000,"pop":0,"sys":{"pod":"d"},"dt_txt":"2026-03-03 09:00:00"},{"dt":1772539200,"main":{"temp":16.63,"feels_like":16.02,"temp_min":16.63,"temp_max":16.63,"pressure":1021,"sea_level":1021,"grnd_level":1013,"humidity":64,"temp_kf":0},"weather":[{"id":804,"main":"Clouds","description":"ennuvolat","icon":"04d"}],"clouds":{"all":93},"wind":{"speed":8.54,"deg":60,"gust":12.15},"visibility":10000,"pop":0,"sys":{"pod":"d"},"dt_txt":"2026-03-03 12:00:00"},{"dt":1772550000,"main":{"temp":16.24,"feels_like":15.7,"temp_min":16.24,"temp_max":16.24,"pressure":1020,"sea_level":1020,"grnd_level":1012,"humidity":68,"temp_kf":0},"weather":[{"id":804,"main":"Clouds","description":"ennuvolat","icon":"04d"}],"clouds":{"all":100},"wind":{"speed":8.66,"deg":62,"gust":12.83},"visibility":10000,"pop":0,"sys":{"pod":"d"},"dt_txt":"2026-03-03 15:00:00"},{"dt":1772560800,"main":{"temp":14.76,"feels_like":14.2,"temp_min":14.76,"temp_max":14.76,"pressure":1021,"sea_level":1021,"grnd_level":1013,"humidity":73,"temp_kf":0},"weather":[{"id":804,"main":"Clouds","description":"ennuvolat","icon":"04n"}],"clouds":{"all":100},"wind":{"speed":6.76,"deg":43,"gust":13.69},"visibility":10000,"pop":0,"sys":{"pod":"n"},"dt_txt":"2026-03-03 18:00:00"},{"dt":1772571600,"main":{"temp":14.06,"feels_like":13.45,"temp_min":14.06,"temp_max":14.06,"pressure":1022,"sea_level":1022,"grnd_level":1014,"humidity":74,"temp_kf":0},"weather":[{"id":804,"main":"Clouds","description":"ennuvolat","icon":"04n"}],"clouds":{"all":100},"wind":{"speed":6.16,"deg":42,"gust":13.64},"visibility":10000,"pop":0,"sys":{"pod":"n"},"dt_txt":"2026-03-03 21:00:00"},{"dt":1772582400,"main":{"temp":14.22,"feels_like":13.55,"temp_min":14.22,"temp_max":14.22,"pressure":1021,"sea_level":1021,"grnd_level":1013,"humidity":71,"temp_kf":0},"weather":[{"id":804,"main":"Clouds","description":"ennuvolat","icon":"04n"}],"clouds":{"all":100},"wind":{"speed":6.13,"deg":41,"gust":13.43},"visibility":10000,"pop":0,"sys":{"pod":"n"},"dt_txt":"2026-03-04 00:00:00"},{"dt":1772593200,"main":{"temp":12.85,"feels_like":12.23,"temp_min":12.85,"temp_max":12.85,"pressure":1021,"sea_level":1021,"grnd_level":1013,"humidity":78,"temp_kf":0},"weather":[{"id":803,"main":"Clouds","description":"nuvolositat variable","icon":"04n"}],"clouds":{"all":51},"wind":{"speed":5.57,"deg":35,"gust":12.21},"visibility":10000,"pop":0,"sys":{"pod":"n"},"dt_txt":"2026-03-04 03:00:00"},{"dt":1772604000,"main":{"temp":12.5,"feels_like":11.95,"temp_min":12.5,"temp_max":12.5,"pressure":1021,"sea_level":1021,"grnd_level":1013,"humidity":82,"temp_kf":0},"weather":[{"id":803,"main":"Clouds","description":"nuvolositat variable","icon":"04n"}],"clouds":{"all":73},"wind":{"speed":5.7,"deg":38,"gust":11.5},"visibility":10000,"pop":0,"sys":{"pod":"n"},"dt_txt":"2026-03-04 06:00:00"},{"dt":1772614800,"main":{"temp":15.28,"feels_like":14.56,"temp_min":15.28,"temp_max":15.28,"pressure":1021,"sea_level":1021,"grnd_level":1013,"humidity":65,"temp_kf":0},"weather":[{"id":803,"main":"Clouds","description":"nuvolositat variable","icon":"04d"}],"clouds":{"all":70},"wind":{"speed":7.92,"deg":55,"gust":13.11},"visibility":10000,"pop":0,"sys":{"pod":"d"},"dt_txt":"2026-03-04 09:00:00"},{"dt":1772625600,"main":{"temp":16.23,"feels_like":15.61,"temp_min":16.23,"temp_max":16.23,"pressure":1021,"sea_level":1021,"grnd_level":1013,"humidity":65,"temp_kf":0},"weather":[{"id":804,"main":"Clouds","description":"ennuvolat","icon":"04d"}],"clouds":{"all":85},"wind":{"speed":9.86,"deg":65,"gust":13.88},"visibility":10000,"pop":0,"sys":{"pod":"d"},"dt_txt":"2026-03-04 12:00:00"},{"dt":1772636400,"main":{"temp":16.31,"feels_like":15.72,"temp_min":16.31,"temp_max":16.31,"pressure":1019,"sea_level":1019,"grnd_level":1011,"humidity":66,"temp_kf":0},"weather":[{"id":804,"main":"Clouds","description":"ennuvolat","icon":"04d"}],"clouds":{"all":100},"wind":{"speed":10.24,"deg":71,"gust":15.16},"visibility":10000,"pop":0,"sys":{"pod":"d"},"dt_txt":"2026-03-04 15:00:00"},{"dt":1772647200,"main":{"temp":14.46,"feels_like":13.89,"temp_min":14.46,"temp_max":14.46,"pressure":1018,"sea_level":1018,"grnd_level":1010,"humidity":74,"temp_kf":0},"weather":[{"id":804,"main":"Clouds","description":"ennuvolat","icon":"04n"}],"clouds":{"all":100},"wind":{"speed":9.17,"deg":54,"gust":16.25},"visibility":10000,"pop":0,"sys":{"pod":"n"},"dt_txt":"2026-03-04 18:00:00"},{"dt":1772658000,"main":{"temp":14.15,"feels_like":13.61,"temp_min":14.15,"temp_max":14.15,"pressure":1018,"sea_level":1018,"grnd_level":1010,"humidity":76,"temp_kf":0},"weather":[{"id":804,"main":"Clouds","description":"ennuvolat","icon":"04n"}],"clouds":{"all":100},"wind":{"speed":8.56,"deg":46,"gust":15.38},"visibility":10000,"pop":0,"sys":{"pod":"n"},"dt_txt":"2026-03-04 21:00:00"},{"dt":1772668800,"main":{"temp":13.86,"feels_like":13.31,"temp_min":13.86,"temp_max":13.86,"pressure":1017,"sea_level":1017,"grnd_level":1009,"humidity":77,"temp_kf":0},"weather":[{"id":804,"main":"Clouds","description":"ennuvolat","icon":"04n"}],"clouds":{"all":100},"wind":{"speed":9.05,"deg":47,"gust":15.82},"visibility":10000,"pop":0,"sys":{"pod":"n"},"dt_txt":"2026-03-05 00:00:00"},{"dt":1772679600,"main":{"temp":13.55,"feels_like":13.13,"temp_min":13.55,"temp_max":13.55,"pressure":1015,"sea_level":1015,"grnd_level":1007,"humidity":83,"temp_kf":0},"weather":[{"id":500,"main":"Rain","description":"pluja suau","icon":"10n"}],"clouds":{"all":100},"wind":{"speed":7.29,"deg":53,"gust":13.34},"visibility":10000,"pop":1,"rain":{"3h":1.32},"sys":{"pod":"n"},"dt_txt":"2026-03-05 03:00:00"},{"dt":1772690400,"main":{"temp":13.01,"feels_like":12.74,"temp_min":13.01,"temp_max":13.01,"pressure":1014,"sea_level":1014,"grnd_level":1007,"humidity":91,"temp_kf":0},"weather":[{"id":500,"main":"Rain","description":"pluja suau","icon":"10n"}],"clouds":{"all":100},"wind":{"speed":6.43,"deg":51,"gust":12.29},"visibility":8583,"pop":1,"rain":{"3h":1.96},"sys":{"pod":"n"},"dt_txt":"2026-03-05 06:00:00"},{"dt":1772701200,"main":{"temp":13.12,"feels_like":12.92,"temp_min":13.12,"temp_max":13.12,"pressure":1013,"sea_level":1013,"grnd_level":1005,"humidity":93,"temp_kf":0},"weather":[{"id":500,"main":"Rain","description":"pluja suau","icon":"10d"}],"clouds":{"all":100},"wind":{"speed":9.23,"deg":52,"gust":14.04},"visibility":10000,"pop":1,"rain":{"3h":2.19},"sys":{"pod":"d"},"dt_txt":"2026-03-05 09:00:00"},{"dt":1772712000,"main":{"temp":13.27,"feels_like":13.16,"temp_min":13.27,"temp_max":13.27,"pressure":1013,"sea_level":1013,"grnd_level":1005,"humidity":96,"temp_kf":0},"weather":[{"id":501,"main":"Rain","description":"pluja","icon":"10d"}],"clouds":{"all":100},"wind":{"speed":6.21,"deg":73,"gust":10.73},"visibility":5019,"pop":1,"rain":{"3h":3.33},"sys":{"pod":"d"},"dt_txt":"2026-03-05 12:00:00"},{"dt":1772722800,"main":{"temp":13.47,"feels_like":13.27,"temp_min":13.47,"temp_max":13.47,"pressure":1012,"sea_level":1012,"grnd_level":1004,"humidity":92,"temp_kf":0},"weather":[{"id":501,"main":"Rain","description":"pluja","icon":"10d"}],"clouds":{"all":100},"wind":{"speed":5.37,"deg":78,"gust":8.71},"visibility":10000,"pop":1,"rain":{"3h":3.41},"sys":{"pod":"d"},"dt_txt":"2026-03-05 15:00:00"},{"dt":1772733600,"main":{"temp":13.39,"feels_like":13.27,"temp_min":13.39,"temp_max":13.39,"pressure":1013,"sea_level":1013,"grnd_level":1005,"humidity":95,"temp_kf":0},"weather":[{"id":500,"main":"Rain","description":"pluja suau","icon":"10n"}],"clouds":{"all":97},"wind":{"speed":5.74,"deg":79,"gust":9.05},"visibility":7343,"pop":1,"rain":{"3h":2.02},"sys":{"pod":"n"},"dt_txt":"2026-03-05 18:00:00"},{"dt":1772744400,"main":{"temp":13.31,"feels_like":13.15,"temp_min":13.31,"temp_max":13.31,"pressure":1014,"sea_level":1014,"grnd_level":1006,"humidity":94,"temp_kf":0},"weather":[{"id":500,"main":"Rain","description":"pluja suau","icon":"10n"}],"clouds":{"all":100},"wind":{"speed":6.43,"deg":90,"gust":10.19},"visibility":3639,"pop":1,"rain":{"3h":2.22},"sys":{"pod":"n"},"dt_txt":"2026-03-05 21:00:00"},{"dt":1772755200,"main":{"temp":13.06,"feels_like":12.93,"temp_min":13.06,"temp_max":13.06,"pressure":1013,"sea_level":1013,"grnd_level":1005,"humidity":96,"temp_kf":0},"weather":[{"id":501,"main":"Rain","description":"pluja","icon":"10n"}],"clouds":{"all":100},"wind":{"speed":6.56,"deg":86,"gust":9.84},"visibility":5167,"pop":1,"rain":{"3h":3.18},"sys":{"pod":"n"},"dt_txt":"2026-03-06 00:00:00"},{"dt":1772766000,"main":{"temp":12.83,"feels_like":12.73,"temp_min":12.83,"temp_max":12.83,"pressure":1013,"sea_level":1013,"grnd_level":1005,"humidity":98,"temp_kf":0},"weather":[{"id":501,"main":"Rain","description":"pluja","icon":"10n"}],"clouds":{"all":100},"wind":{"speed":4.81,"deg":94,"gust":8.1},"visibility":3192,"pop":1,"rain":{"3h":3.44},"sys":{"pod":"n"},"dt_txt":"2026-03-06 03:00:00"},{"dt":1772776800,"main":{"temp":12.69,"feels_like":12.52,"temp_min":12.69,"temp_max":12.69,"pressure":1013,"sea_level":1013,"grnd_level":1005,"humidity":96,"temp_kf":0},"weather":[{"id":500,"main":"Rain","description":"pluja suau","icon":"10n"}],"clouds":{"all":100},"wind":{"speed":2.22,"deg":72,"gust":3.55},"visibility":7284,"pop":1,"rain":{"3h":1.88},"sys":{"pod":"n"},"dt_txt":"2026-03-06 06:00:00"},{"dt":1772787600,"main":{"temp":13.86,"feels_like":13.55,"temp_min":13.86,"temp_max":13.86,"pressure":1015,"sea_level":1015,"grnd_level":1007,"humidity":86,"temp_kf":0},"weather":[{"id":500,"main":"Rain","description":"pluja suau","icon":"10d"}],"clouds":{"all":91},"wind":{"speed":3.84,"deg":58,"gust":5.09},"visibility":10000,"pop":1,"rain":{"3h":1.81},"sys":{"pod":"d"},"dt_txt":"2026-03-06 09:00:00"},{"dt":1772798400,"main":{"temp":15.42,"feels_like":15,"temp_min":15.42,"temp_max":15.42,"pressure":1015,"sea_level":1015,"grnd_level":1007,"humidity":76,"temp_kf":0},"weather":[{"id":500,"main":"Rain","description":"pluja suau","icon":"10d"}],"clouds":{"all":65},"wind":{"speed":2.39,"deg":100,"gust":2.84},"visibility":10000,"pop":1,"rain":{"3h":2.07},"sys":{"pod":"d"},"dt_txt":"2026-03-06 12:00:00"},{"dt":1772809200,"main":{"temp":15.52,"feels_like":15.06,"temp_min":15.52,"temp_max":15.52,"pressure":1015,"sea_level":1015,"grnd_level":1007,"humidity":74,"temp_kf":0},"weather":[{"id":500,"main":"Rain","description":"pluja suau","icon":"10d"}],"clouds":{"all":99},"wind":{"speed":3.15,"deg":121,"gust":3.69},"visibility":10000,"pop":0.73,"rain":{"3h":0.49},"sys":{"pod":"d"},"dt_txt":"2026-03-06 15:00:00"},{"dt":1772820000,"main":{"temp":13.68,"feels_like":13.3,"temp_min":13.68,"temp_max":13.68,"pressure":1017,"sea_level":1017,"grnd_level":1009,"humidity":84,"temp_kf":0},"weather":[{"id":500,"main":"Rain","description":"pluja suau","icon":"10n"}],"clouds":{"all":76},"wind":{"speed":1.98,"deg":110,"gust":3.88},"visibility":10000,"pop":0.79,"rain":{"3h":0.76},"sys":{"pod":"n"},"dt_txt":"2026-03-06 18:00:00"},{"dt":1772830800,"main":{"temp":12.89,"feels_like":12.53,"temp_min":12.89,"temp_max":12.89,"pressure":1019,"sea_level":1019,"grnd_level":1011,"humidity":88,"temp_kf":0},"weather":[{"id":500,"main":"Rain","description":"pluja suau","icon":"10n"}],"clouds":{"all":47},"wind":{"speed":2.68,"deg":58,"gust":4.2},"visibility":10000,"pop":0.35,"rain":{"3h":0.3},"sys":{"pod":"n"},"dt_txt":"2026-03-06 21:00:00"},{"dt":1772841600,"main":{"temp":12.75,"feels_like":12.3,"temp_min":12.75,"temp_max":12.75,"pressure":1020,"sea_level":1020,"grnd_level":1012,"humidity":85,"temp_kf":0},"weather":[{"id":500,"main":"Rain","description":"pluja suau","icon":"10n"}],"clouds":{"all":66},"wind":{"speed":2.55,"deg":44,"gust":3.13},"visibility":10000,"pop":0.4,"rain":{"3h":0.21},"sys":{"pod":"n"},"dt_txt":"2026-03-07 00:00:00"},{"dt":1772852400,"main":{"temp":12.68,"feels_like":12.14,"temp_min":12.68,"temp_max":12.68,"pressure":1020,"sea_level":1020,"grnd_level":1012,"humidity":82,"temp_kf":0},"weather":[{"id":500,"main":"Rain","description":"pluja suau","icon":"10n"}],"clouds":{"all":70},"wind":{"speed":2.15,"deg":34,"gust":2.46},"visibility":10000,"pop":0.46,"rain":{"3h":0.24},"sys":{"pod":"n"},"dt_txt":"2026-03-07 03:00:00"},{"dt":1772863200,"main":{"temp":11.72,"feels_like":11.14,"temp_min":11.72,"temp_max":11.72,"pressure":1021,"sea_level":1021,"grnd_level":1013,"humidity":84,"temp_kf":0},"weather":[{"id":500,"main":"Rain","description":"pluja suau","icon":"10n"}],"clouds":{"all":43},"wind":{"speed":0.52,"deg":48,"gust":0.91},"visibility":10000,"pop":0.54,"rain":{"3h":0.27},"sys":{"pod":"n"},"dt_txt":"2026-03-07 06:00:00"}],"city":{"id":6356147,"name":"Masnou, El","coord":{"lat":41.4853,"lon":2.3275},"country":"ES","population":22288,"timezone":3600,"sunrise":1772432660,"sunset":1772473305}}