{"cod":"200","message":0,"cnt":40,"list":[{"dt":1783047600,"main":{"temp":25.8,"feels_like":25.66,"temp_min":24.01,"temp_max":25.8,"pressure":1020,"sea_level":1020,"grnd_level":1012,"humidity":47,"temp_kf":1.79,"dew_point":13.64},"weather":[{"id":801,"main":"Clouds","description":"lleugerament ennuvolat","icon":"02n"}],"clouds":{"all":20},"wind":{"speed":1.9,"deg":23,"gust":2.06},"visibility":10000,"pop":0,"sys":{"pod":"n"},"dt_txt":"2026-07-03 03:00:00"},{"dt":1783058400,"main":{"temp":26.32,"feels_like":26.32,"temp_min":26.13,"temp_max":26.32,"pressure":1021,"sea_level":1021,"grnd_level":1013,"humidity":43,"temp_kf":0.19,"dew_point":12.75},"weather":[{"id":801,"main":"Clouds","description":"lleugerament ennuvolat","icon":"02d"}],"clouds":{"all":22},"wind":{"speed":1.35,"deg":289,"gust":1.83},"visibility":10000,"pop":0,"sys":{"pod":"d"},"dt_txt":"2026-07-03 06:00:00"},{"dt":1783069200,"main":{"temp":31.58,"feels_like":30.81,"temp_min":31.58,"temp_max":31.58,"pressure":1021,"sea_level":1021,"grnd_level":1014,"humidity":34,"temp_kf":0,"dew_point":10.94},"weather":[{"id":800,"main":"Clear","description":"cel net","icon":"01d"}],"clouds":{"all":0},"wind":{"speed":1.68,"deg":197,"gust":2.26},"visibility":10000,"pop":0,"sys":{"pod":"d"},"dt_txt":"2026-07-03 09:00:00"},{"dt":1783080000,"main":{"temp":33.17,"feels_like":35,"temp_min":33.17,"temp_max":33.17,"pressure":1021,"sea_level":1021,"grnd_level":1013,"humidity":44,"temp_kf":0,"dew_point":15.11},"weather":[{"id":800,"main":"Clear","description":"cel net","icon":"01d"}],"clouds":{"all":0},"wind":{"speed":6.15,"deg":162,"gust":5.2},"visibility":10000,"pop":0,"sys":{"pod":"d"},"dt_txt":"2026-07-03 12:00:00"},{"dt":1783090800,"main":{"temp":32.31,"feels_like":34.94,"temp_min":32.31,"temp_max":32.31,"pressure":1021,"sea_level":1021,"grnd_level":1013,"humidity":50,"temp_kf":0,"dew_point":16.71},"weather":[{"id":800,"main":"Clear","description":"cel net","icon":"01d"}],"clouds":{"all":0},"wind":{"speed":3.95,"deg":154,"gust":4.19},"visibility":10000,"pop":0,"sys":{"pod":"d"},"dt_txt":"2026-07-03 15:00:00"},{"dt":1783101600,"main":{"temp":30.25,"feels_like":32.31,"temp_min":30.25,"temp_max":30.25,"pressure":1021,"sea_level":1021,"grnd_level":1014,"humidity":55,"temp_kf":0,"dew_point":17.1},"weather":[{"id":800,"main":"Clear","description":"cel net","icon":"01d"}],"clouds":{"all":0},"wind":{"speed":1.63,"deg":164,"gust":2.31},"visibility":10000,"pop":0,"sys":{"pod":"d"},"dt_txt":"2026-07-03 18:00:00"},{"dt":1783112400,"main":{"temp":28.17,"feels_like":29.04,"temp_min":28.17,"temp_max":28.17,"pressure":1022,"sea_level":1022,"grnd_level":1015,"humidity":54,"temp_kf":0,"dew_point":16.48},"weather":[{"id":800,"main":"Clear","description":"cel net","icon":"01n"}],"clouds":{"all":0},"wind":{"speed":1.56,"deg":255,"gust":2.31},"visibility":10000,"pop":0,"sys":{"pod":"n"},"dt_txt":"2026-07-03 21:00:00"},{"dt":1783123200,"main":{"temp":27.06,"feels_like":27.41,"temp_min":27.06,"temp_max":27.06,"pressure":1022,"sea_level":1022,"grnd_level":1014,"humidity":49,"temp_kf":0,"dew_point":15.08},"weather":[{"id":800,"main":"Clear","description":"cel net","icon":"01n"}],"clouds":{"all":0},"wind":{"speed":2.28,"deg":276,"gust":2.76},"visibility":10000,"pop":0,"sys":{"pod":"n"},"dt_txt":"2026-07-04 00:00:00"},{"dt":1783134000,"main":{"temp":26.02,"feels_like":26.02,"temp_min":26.02,"temp_max":26.02,"pressure":1022,"sea_level":1022,"grnd_level":1014,"humidity":48,"temp_kf":0,"dew_point":14.04},"weather":[{"id":800,"main":"Clear","description":"cel net","icon":"01n"}],"clouds":{"all":0},"wind":{"speed":1.34,"deg":313,"gust":1.58},"visibility":10000,"pop":0,"sys":{"pod":"n"},"dt_txt":"2026-07-04 03:00:00"},{"dt":1783144800,"main":{"temp":27.85,"feels_like":27.96,"temp_min":27.85,"temp_max":27.85,"pressure":1022,"sea_level":1022,"grnd_level":1015,"humidity":46,"temp_kf":0,"dew_point":13.58},"weather":[{"id":800,"main":"Clear","description":"cel net","icon":"01d"}],"clouds":{"all":0},"wind":{"speed":0.64,"deg":352,"gust":1.27},"visibility":10000,"pop":0,"sys":{"pod":"d"},"dt_txt":"2026-07-04 06:00:00"},{"dt":1783155600,"main":{"temp":32.65,"feels_like":33.04,"temp_min":32.65,"temp_max":32.65,"pressure":1022,"sea_level":1022,"grnd_level":1015,"humidity":39,"temp_kf":0,"dew_point":13.29},"weather":[{"id":800,"main":"Clear","description":"cel net","icon":"01d"}],"clouds":{"all":0},"wind":{"speed":2,"deg":160,"gust":1.14},"visibility":10000,"pop":0,"sys":{"pod":"d"},"dt_txt":"2026-07-04 09:00:00"},{"dt":1783166400,"main":{"temp":33.89,"feels_like":36.6,"temp_min":33.89,"temp_max":33.89,"pressure":1022,"sea_level":1022,"grnd_level":1015,"humidity":45,"temp_kf":0,"dew_point":15.68},"weather":[{"id":800,"main":"Clear","description":"cel net","icon":"01d"}],"clouds":{"all":0},"wind":{"speed":4.21,"deg":168,"gust":3.5},"visibility":10000,"pop":0,"sys":{"pod":"d"},"dt_txt":"2026-07-04 12:00:00"},{"dt":1783177200,"main":{"temp":33.24,"feels_like":35.64,"temp_min":33.24,"temp_max":33.24,"pressure":1022,"sea_level":1022,"grnd_level":1014,"humidity":46,"temp_kf":0,"dew_point":16.13},"weather":[{"id":800,"main":"Clear","description":"cel net","icon":"01d"}],"clouds":{"all":0},"wind":{"speed":3.05,"deg":176,"gust":3.82},"visibility":10000,"pop":0,"sys":{"pod":"d"},"dt_txt":"2026-07-04 15:00:00"},{"dt":1783188000,"main":{"temp":32.08,"feels_like":35.01,"temp_min":32.08,"temp_max":32.08,"pressure":1021,"sea_level":1021,"grnd_level":1013,"humidity":52,"temp_kf":0,"dew_point":17.1},"weather":[{"id":800,"main":"Clear","description":"cel net","icon":"01d"}],"clouds":{"all":0},"wind":{"speed":3.06,"deg":203,"gust":4.21},"visibility":10000,"pop":0,"sys":{"pod":"d"},"dt_txt":"2026-07-04 18:00:00"},{"dt":1783198800,"main":{"temp":28.39,"feels_like":28.9,"temp_min":28.39,"temp_max":28.39,"pressure":1021,"sea_level":1021,"grnd_level":1014,"humidity":50,"temp_kf":0,"dew_point":16.26},"weather":[{"id":800,"main":"Clear","description":"cel net","icon":"01n"}],"clouds":{"all":0},"wind":{"speed":2.95,"deg":246,"gust":3.89},"visibility":10000,"pop":0,"sys":{"pod":"n"},"dt_txt":"2026-07-04 21:00:00"},{"dt":1783209600,"main":{"temp":27.77,"feels_like":28.11,"temp_min":27.77,"temp_max":27.77,"pressure":1021,"sea_level":1021,"grnd_level":1013,"humidity":49,"temp_kf":0,"dew_point":15.64},"weather":[{"id":800,"main":"Clear","description":"cel net","icon":"01n"}],"clouds":{"all":0},"wind":{"speed":1.73,"deg":279,"gust":2.07},"visibility":10000,"pop":0,"sys":{"pod":"n"},"dt_txt":"2026-07-05 00:00:00"},{"dt":1783220400,"main":{"temp":26.6,"feels_like":26.6,"temp_min":26.6,"temp_max":26.6,"pressure":1020,"sea_level":1020,"grnd_level":1013,"humidity":50,"temp_kf":0,"dew_point":15.1},"weather":[{"id":800,"main":"Clear","description":"cel net","icon":"01n"}],"clouds":{"all":0},"wind":{"speed":1.65,"deg":314,"gust":1.98},"visibility":10000,"pop":0,"sys":{"pod":"n"},"dt_txt":"2026-07-05 03:00:00"},{"dt":1783231200,"main":{"temp":27.46,"feels_like":27.73,"temp_min":27.46,"temp_max":27.46,"pressure":1021,"sea_level":1021,"grnd_level":1013,"humidity":48,"temp_kf":0,"dew_point":15.3},"weather":[{"id":800,"main":"Clear","description":"cel net","icon":"01d"}],"clouds":{"all":0},"wind":{"speed":1.12,"deg":324,"gust":1.21},"visibility":10000,"pop":0,"sys":{"pod":"d"},"dt_txt":"2026-07-05 06:00:00"},{"dt":1783242000,"main":{"temp":30.87,"feels_like":30.23,"temp_min":30.87,"temp_max":30.87,"pressure":1020,"sea_level":1020,"grnd_level":1012,"humidity":36,"temp_kf":0,"dew_point":13.19},"weather":[{"id":800,"main":"Clear","description":"cel net","icon":"01d"}],"clouds":{"all":0},"wind":{"speed":1.56,"deg":157,"gust":1.14},"visibility":10000,"pop":0,"sys":{"pod":"d"},"dt_txt":"2026-07-05 09:00:00"},{"dt":1783252800,"main":{"temp":30.96,"feels_like":29.88,"temp_min":30.96,"temp_max":30.96,"pressure":1020,"sea_level":1020,"grnd_level":1012,"humidity":32,"temp_kf":0,"dew_point":11.17},"weather":[{"id":800,"main":"Clear","description":"cel net","icon":"01d"}],"clouds":{"all":0},"wind":{"speed":5.15,"deg":163,"gust":4.03},"visibility":10000,"pop":0,"sys":{"pod":"d"},"dt_txt":"2026-07-05 12:00:00"},{"dt":1783263600,"main":{"temp":30.35,"feels_like":31.09,"temp_min":30.35,"temp_max":30.35,"pressure":1019,"sea_level":1019,"grnd_level":1011,"humidity":47,"temp_kf":0,"dew_point":16.81},"weather":[{"id":800,"main":"Clear","description":"cel net","icon":"01d"}],"clouds":{"all":0},"wind":{"speed":4.02,"deg":172,"gust":4.53},"visibility":10000,"pop":0,"sys":{"pod":"d"},"dt_txt":"2026-07-05 15:00:00"},{"dt":1783274400,"main":{"temp":29.3,"feels_like":29.93,"temp_min":29.3,"temp_max":29.3,"pressure":1019,"sea_level":1019,"grnd_level":1011,"humidity":49,"temp_kf":0,"dew_point":16.58},"weather":[{"id":800,"main":"Clear","description":"cel net","icon":"01d"}],"clouds":{"all":0},"wind":{"speed":3.35,"deg":214,"gust":4.84},"visibility":10000,"pop":0,"sys":{"pod":"d"},"dt_txt":"2026-07-05 18:00:00"},{"dt":1783285200,"main":{"temp":29.12,"feels_like":29.23,"temp_min":29.12,"temp_max":29.12,"pressure":1019,"sea_level":1019,"grnd_level":1011,"humidity":45,"temp_kf":0,"dew_point":14.82},"weather":[{"id":800,"main":"Clear","description":"cel net","icon":"01n"}],"clouds":{"all":0},"wind":{"speed":3.78,"deg":258,"gust":6.08},"visibility":10000,"pop":0,"sys":{"pod":"n"},"dt_txt":"2026-07-05 21:00:00"},{"dt":1783296000,"main":{"temp":28.31,"feels_like":28.02,"temp_min":28.31,"temp_max":28.31,"pressure":1018,"sea_level":1018,"grnd_level":1011,"humidity":41,"temp_kf":0,"dew_point":13.29},"weather":[{"id":800,"main":"Clear","description":"cel net","icon":"01n"}],"clouds":{"all":0},"wind":{"speed":2.75,"deg":277,"gust":3.18},"visibility":10000,"pop":0,"sys":{"pod":"n"},"dt_txt":"2026-07-06 00:00:00"},{"dt":1783306800,"main":{"temp":27.16,"feels_like":27.03,"temp_min":27.16,"temp_max":27.16,"pressure":1018,"sea_level":1018,"grnd_level":1010,"humidity":41,"temp_kf":0,"dew_point":12.43},"weather":[{"id":800,"main":"Clear","description":"cel net","icon":"01n"}],"clouds":{"all":0},"wind":{"speed":1.71,"deg":325,"gust":1.62},"visibility":10000,"pop":0,"sys":{"pod":"n"},"dt_txt":"2026-07-06 03:00:00"},{"dt":1783317600,"main":{"temp":27.86,"feels_like":27.54,"temp_min":27.86,"temp_max":27.86,"pressure":1018,"sea_level":1018,"grnd_level":1010,"humidity":40,"temp_kf":0,"dew_point":12.62},"weather":[{"id":800,"main":"Clear","description":"cel net","icon":"01d"}],"clouds":{"all":0},"wind":{"speed":1.2,"deg":322,"gust":1.4},"visibility":10000,"pop":0,"sys":{"pod":"d"},"dt_txt":"2026-07-06 06:00:00"},{"dt":1783328400,"main":{"temp":30.92,"feels_like":30.05,"temp_min":30.92,"temp_max":30.92,"pressure":1018,"sea_level":1018,"grnd_level":1011,"humidity":34,"temp_kf":0,"dew_point":11.97},"weather":[{"id":800,"main":"Clear","description":"cel net","icon":"01d"}],"clouds":{"all":0},"wind":{"speed":1.7,"deg":169,"gust":1.95},"visibility":10000,"pop":0,"sys":{"pod":"d"},"dt_txt":"2026-07-06 09:00:00"},{"dt":1783339200,"main":{"temp":31.24,"feels_like":30.42,"temp_min":31.24,"temp_max":31.24,"pressure":1018,"sea_level":1018,"grnd_level":1011,"humidity":34,"temp_kf":0,"dew_point":12.69},"weather":[{"id":800,"main":"Clear","description":"cel net","icon":"01d"}],"clouds":{"all":0},"wind":{"speed":3.75,"deg":184,"gust":3.54},"visibility":10000,"pop":0,"sys":{"pod":"d"},"dt_txt":"2026-07-06 12:00:00"},{"dt":1783350000,"main":{"temp":31.09,"feels_like":30.89,"temp_min":31.09,"temp_max":31.09,"pressure":1017,"sea_level":1017,"grnd_level":1010,"humidity":39,"temp_kf":0,"dew_point":14.24},"weather":[{"id":800,"main":"Clear","description":"cel net","icon":"01d"}],"clouds":{"all":0},"wind":{"speed":4.77,"deg":189,"gust":5.8},"visibility":10000,"pop":0,"sys":{"pod":"d"},"dt_txt":"2026-07-06 15:00:00"},{"dt":1783360800,"main":{"temp":29.75,"feels_like":30.13,"temp_min":29.75,"temp_max":29.75,"pressure":1017,"sea_level":1017,"grnd_level":1010,"humidity":46,"temp_kf":0,"dew_point":15.92},"weather":[{"id":800,"main":"Clear","description":"cel net","icon":"01d"}],"clouds":{"all":1},"wind":{"speed":2.22,"deg":203,"gust":3.07},"visibility":10000,"pop":0,"sys":{"pod":"d"},"dt_txt":"2026-07-06 18:00:00"},{"dt":1783371600,"main":{"temp":28.6,"feels_like":28.84,"temp_min":28.6,"temp_max":28.6,"pressure":1018,"sea_level":1018,"grnd_level":1010,"humidity":47,"temp_kf":0,"dew_point":15.49},"weather":[{"id":800,"main":"Clear","description":"cel net","icon":"01n"}],"clouds":{"all":3},"wind":{"speed":2.81,"deg":239,"gust":3.63},"visibility":10000,"pop":0,"sys":{"pod":"n"},"dt_txt":"2026-07-06 21:00:00"},{"dt":1783382400,"main":{"temp":28.27,"feels_like":28.22,"temp_min":28.27,"temp_max":28.27,"pressure":1018,"sea_level":1018,"grnd_level":1010,"humidity":44,"temp_kf":0,"dew_point":14.43},"weather":[{"id":800,"main":"Clear","description":"cel net","icon":"01n"}],"clouds":{"all":3},"wind":{"speed":2.46,"deg":264,"gust":2.65},"visibility":10000,"pop":0,"sys":{"pod":"n"},"dt_txt":"2026-07-07 00:00:00"},{"dt":1783393200,"main":{"temp":27.36,"feels_like":27.31,"temp_min":27.36,"temp_max":27.36,"pressure":1017,"sea_level":1017,"grnd_level":1009,"humidity":43,"temp_kf":0,"dew_point":13.42},"weather":[{"id":800,"main":"Clear","description":"cel net","icon":"01n"}],"clouds":{"all":0},"wind":{"speed":2.31,"deg":263,"gust":2.43},"visibility":10000,"pop":0,"sys":{"pod":"n"},"dt_txt":"2026-07-07 03:00:00"},{"dt":1783404000,"main":{"temp":27.76,"feels_like":27.46,"temp_min":27.76,"temp_max":27.76,"pressure":1017,"sea_level":1017,"grnd_level":1009,"humidity":40,"temp_kf":0,"dew_point":12.63},"weather":[{"id":800,"main":"Clear","description":"cel net","icon":"01d"}],"clouds":{"all":1},"wind":{"speed":1.7,"deg":272,"gust":1.99},"visibility":10000,"pop":0,"sys":{"pod":"d"},"dt_txt":"2026-07-07 06:00:00"},{"dt":1783414800,"main":{"temp":30.63,"feels_like":29.63,"temp_min":30.63,"temp_max":30.63,"pressure":1018,"sea_level":1018,"grnd_level":1010,"humidity":33,"temp_kf":0,"dew_point":11.41},"weather":[{"id":800,"main":"Clear","description":"cel net","icon":"01d"}],"clouds":{"all":1},"wind":{"speed":2.23,"deg":153,"gust":2.47},"visibility":10000,"pop":0,"sys":{"pod":"d"},"dt_txt":"2026-07-07 09:00:00"},{"dt":1783425600,"main":{"temp":29.86,"feels_like":29.64,"temp_min":29.86,"temp_max":29.86,"pressure":1019,"sea_level":1019,"grnd_level":1011,"humidity":41,"temp_kf":0,"dew_point":14.7},"weather":[{"id":800,"main":"Clear","description":"cel net","icon":"01d"}],"clouds":{"all":3},"wind":{"speed":3.26,"deg":166,"gust":3.6},"visibility":10000,"pop":0,"sys":{"pod":"d"},"dt_txt":"2026-07-07 12:00:00"},{"dt":1783436400,"main":{"temp":30.3,"feels_like":30.86,"temp_min":30.3,"temp_max":30.3,"pressure":1018,"sea_level":1018,"grnd_level":1010,"humidity":46,"temp_kf":0,"dew_point":16.85},"weather":[{"id":800,"main":"Clear","description":"cel net","icon":"01d"}],"clouds":{"all":9},"wind":{"speed":2.67,"deg":159,"gust":2.95},"visibility":10000,"pop":0,"sys":{"pod":"d"},"dt_txt":"2026-07-07 15:00:00"},{"dt":1783447200,"main":{"temp":29.84,"feels_like":30.52,"temp_min":29.84,"temp_max":29.84,"pressure":1017,"sea_level":1017,"grnd_level":1010,"humidity":48,"temp_kf":0,"dew_point":17.27},"weather":[{"id":801,"main":"Clouds","description":"lleugerament ennuvolat","icon":"02d"}],"clouds":{"all":17},"wind":{"speed":4.35,"deg":192,"gust":4.87},"visibility":10000,"pop":0,"sys":{"pod":"d"},"dt_txt":"2026-07-07 18:00:00"},{"dt":1783458000,"main":{"temp":28.74,"feels_like":29.56,"temp_min":28.74,"temp_max":28.74,"pressure":1018,"sea_level":1018,"grnd_level":1010,"humidity":52,"temp_kf":0,"dew_point":17.52},"weather":[{"id":802,"main":"Clouds","description":"núvols dispersos","icon":"03n"}],"clouds":{"all":37},"wind":{"speed":4.63,"deg":226,"gust":6.39},"visibility":10000,"pop":0,"sys":{"pod":"n"},"dt_txt":"2026-07-07 21:00:00"},{"dt":1783468800,"main":{"temp":28.1,"feels_like":28.95,"temp_min":28.1,"temp_max":28.1,"pressure":1016,"sea_level":1016,"grnd_level":1008,"humidity":54,"temp_kf":0,"dew_point":17.36},"weather":[{"id":802,"main":"Clouds","description":"núvols dispersos","icon":"03n"}],"clouds":{"all":47},"wind":{"speed":2.39,"deg":245,"gust":2.76},"visibility":10000,"pop":0,"sys":{"pod":"n"},"dt_txt":"2026-07-08 00:00:00"}],"city":{"id":6356147,"name":"Masnou, El","coord":{"lat":41.4853,"lon":2.3275},"country":"ES","population":22288,"timezone":7200,"sunrise":1783052488,"sunset":1783106878}}