{"cod":"200","message":0,"cnt":40,"list":[{"dt":1773219600,"main":{"temp":12.01,"feels_like":11.15,"temp_min":12.01,"temp_max":12.61,"pressure":1023,"sea_level":1023,"grnd_level":1016,"humidity":72,"temp_kf":-0.6},"weather":[{"id":802,"main":"Clouds","description":"núvols dispersos","icon":"03d"}],"clouds":{"all":28},"wind":{"speed":1.17,"deg":286,"gust":1.68},"visibility":10000,"pop":0,"sys":{"pod":"d"},"dt_txt":"2026-03-11 09:00:00"},{"dt":1773230400,"main":{"temp":15.65,"feels_like":14.86,"temp_min":15.65,"temp_max":17.62,"pressure":1023,"sea_level":1023,"grnd_level":1016,"humidity":61,"temp_kf":-1.97},"weather":[{"id":803,"main":"Clouds","description":"nuvolositat variable","icon":"04d"}],"clouds":{"all":58},"wind":{"speed":3.93,"deg":204,"gust":4.08},"visibility":10000,"pop":0,"sys":{"pod":"d"},"dt_txt":"2026-03-11 12:00:00"},{"dt":1773241200,"main":{"temp":18.83,"feels_like":18.2,"temp_min":18.83,"temp_max":18.83,"pressure":1022,"sea_level":1022,"grnd_level":1014,"humidity":55,"temp_kf":0},"weather":[{"id":804,"main":"Clouds","description":"ennuvolat","icon":"04d"}],"clouds":{"all":100},"wind":{"speed":4.9,"deg":215,"gust":6.35},"visibility":10000,"pop":0,"sys":{"pod":"d"},"dt_txt":"2026-03-11 15:00:00"},{"dt":1773252000,"main":{"temp":16.59,"feels_like":15.95,"temp_min":16.59,"temp_max":16.59,"pressure":1023,"sea_level":1023,"grnd_level":1015,"humidity":63,"temp_kf":0},"weather":[{"id":804,"main":"Clouds","description":"ennuvolat","icon":"04n"}],"clouds":{"all":100},"wind":{"speed":2.09,"deg":231,"gust":3.98},"visibility":10000,"pop":0,"sys":{"pod":"n"},"dt_txt":"2026-03-11 18:00:00"},{"dt":1773262800,"main":{"temp":14.17,"feels_like":13.55,"temp_min":14.17,"temp_max":14.17,"pressure":1025,"sea_level":1025,"grnd_level":1017,"humidity":73,"temp_kf":0},"weather":[{"id":804,"main":"Clouds","description":"ennuvolat","icon":"04n"}],"clouds":{"all":100},"wind":{"speed":2.75,"deg":44,"gust":4.41},"visibility":10000,"pop":0,"sys":{"pod":"n"},"dt_txt":"2026-03-11 21:00:00"},{"dt":1773273600,"main":{"temp":10.74,"feels_like":9.91,"temp_min":10.74,"temp_max":10.74,"pressure":1025,"sea_level":1025,"grnd_level":1017,"humidity":78,"temp_kf":0},"weather":[{"id":803,"main":"Clouds","description":"nuvolositat variable","icon":"04n"}],"clouds":{"all":55},"wind":{"speed":2.96,"deg":63,"gust":4.49},"visibility":10000,"pop":0,"sys":{"pod":"n"},"dt_txt":"2026-03-12 00:00:00"},{"dt":1773284400,"main":{"temp":11.92,"feels_like":11.36,"temp_min":11.92,"temp_max":11.92,"pressure":1025,"sea_level":1025,"grnd_level":1017,"humidity":84,"temp_kf":0},"weather":[{"id":800,"main":"Clear","description":"cel net","icon":"01n"}],"clouds":{"all":7},"wind":{"speed":2.6,"deg":43,"gust":2.77},"visibility":10000,"pop":0,"sys":{"pod":"n"},"dt_txt":"2026-03-12 03:00:00"},{"dt":1773295200,"main":{"temp":12.07,"feels_like":11.58,"temp_min":12.07,"temp_max":12.07,"pressure":1024,"sea_level":1024,"grnd_level":1016,"humidity":86,"temp_kf":0},"weather":[{"id":802,"main":"Clouds","description":"núvols dispersos","icon":"03n"}],"clouds":{"all":49},"wind":{"speed":1.38,"deg":88,"gust":2.36},"visibility":10000,"pop":0,"sys":{"pod":"n"},"dt_txt":"2026-03-12 06:00:00"},{"dt":1773306000,"main":{"temp":13.31,"feels_like":12.86,"temp_min":13.31,"temp_max":13.31,"pressure":1025,"sea_level":1025,"grnd_level":1017,"humidity":83,"temp_kf":0},"weather":[{"id":500,"main":"Rain","description":"pluja suau","icon":"10d"}],"clouds":{"all":100},"wind":{"speed":2.55,"deg":177,"gust":3.42},"visibility":10000,"pop":0.23,"rain":{"3h":0.31},"sys":{"pod":"d"},"dt_txt":"2026-03-12 09:00:00"},{"dt":1773316800,"main":{"temp":14.76,"feels_like":14.25,"temp_min":14.76,"temp_max":14.76,"pressure":1024,"sea_level":1024,"grnd_level":1016,"humidity":75,"temp_kf":0},"weather":[{"id":500,"main":"Rain","description":"pluja suau","icon":"10d"}],"clouds":{"all":99},"wind":{"speed":3.34,"deg":182,"gust":3.2},"visibility":10000,"pop":0.23,"rain":{"3h":0.35},"sys":{"pod":"d"},"dt_txt":"2026-03-12 12:00:00"},{"dt":1773327600,"main":{"temp":14.2,"feels_like":13.71,"temp_min":14.2,"temp_max":14.2,"pressure":1023,"sea_level":1023,"grnd_level":1015,"humidity":78,"temp_kf":0},"weather":[{"id":804,"main":"Clouds","description":"ennuvolat","icon":"04d"}],"clouds":{"all":93},"wind":{"speed":2.25,"deg":141,"gust":1.12},"visibility":10000,"pop":0,"sys":{"pod":"d"},"dt_txt":"2026-03-12 15:00:00"},{"dt":1773338400,"main":{"temp":13.2,"feels_like":12.77,"temp_min":13.2,"temp_max":13.2,"pressure":1023,"sea_level":1023,"grnd_level":1015,"humidity":84,"temp_kf":0},"weather":[{"id":803,"main":"Clouds","description":"nuvolositat variable","icon":"04n"}],"clouds":{"all":65},"wind":{"speed":1.03,"deg":102,"gust":1.03},"visibility":10000,"pop":0,"sys":{"pod":"n"},"dt_txt":"2026-03-12 18:00:00"},{"dt":1773349200,"main":{"temp":12.82,"feels_like":12.4,"temp_min":12.82,"temp_max":12.82,"pressure":1024,"sea_level":1024,"grnd_level":1016,"humidity":86,"temp_kf":0},"weather":[{"id":801,"main":"Clouds","description":"lleugerament ennuvolat","icon":"02n"}],"clouds":{"all":12},"wind":{"speed":0.63,"deg":69,"gust":0.55},"visibility":10000,"pop":0,"sys":{"pod":"n"},"dt_txt":"2026-03-12 21:00:00"},{"dt":1773360000,"main":{"temp":12.04,"feels_like":11.6,"temp_min":12.04,"temp_max":12.04,"pressure":1023,"sea_level":1023,"grnd_level":1015,"humidity":88,"temp_kf":0},"weather":[{"id":800,"main":"Clear","description":"cel net","icon":"01n"}],"clouds":{"all":5},"wind":{"speed":0.84,"deg":316,"gust":0.85},"visibility":10000,"pop":0,"sys":{"pod":"n"},"dt_txt":"2026-03-13 00:00:00"},{"dt":1773370800,"main":{"temp":11.63,"feels_like":11.09,"temp_min":11.63,"temp_max":11.63,"pressure":1021,"sea_level":1021,"grnd_level":1013,"humidity":86,"temp_kf":0},"weather":[{"id":800,"main":"Clear","description":"cel net","icon":"01n"}],"clouds":{"all":0},"wind":{"speed":1.36,"deg":297,"gust":1.67},"visibility":10000,"pop":0,"sys":{"pod":"n"},"dt_txt":"2026-03-13 03:00:00"},{"dt":1773381600,"main":{"temp":11.16,"feels_like":10.47,"temp_min":11.16,"temp_max":11.16,"pressure":1020,"sea_level":1020,"grnd_level":1012,"humidity":82,"temp_kf":0},"weather":[{"id":800,"main":"Clear","description":"cel net","icon":"01n"}],"clouds":{"all":2},"wind":{"speed":1.53,"deg":286,"gust":1.71},"visibility":10000,"pop":0,"sys":{"pod":"n"},"dt_txt":"2026-03-13 06:00:00"},{"dt":1773392400,"main":{"temp":13.44,"feels_like":12.67,"temp_min":13.44,"temp_max":13.44,"pressure":1020,"sea_level":1020,"grnd_level":1012,"humidity":70,"temp_kf":0},"weather":[{"id":800,"main":"Clear","description":"cel net","icon":"01d"}],"clouds":{"all":2},"wind":{"speed":2.21,"deg":238,"gust":2.99},"visibility":10000,"pop":0,"sys":{"pod":"d"},"dt_txt":"2026-03-13 09:00:00"},{"dt":1773403200,"main":{"temp":15.87,"feels_like":15.13,"temp_min":15.87,"temp_max":15.87,"pressure":1018,"sea_level":1018,"grnd_level":1010,"humidity":62,"temp_kf":0},"weather":[{"id":800,"main":"Clear","description":"cel net","icon":"01d"}],"clouds":{"all":1},"wind":{"speed":4.6,"deg":205,"gust":5.19},"visibility":10000,"pop":0,"sys":{"pod":"d"},"dt_txt":"2026-03-13 12:00:00"},{"dt":1773414000,"main":{"temp":15.14,"feels_like":14.51,"temp_min":15.14,"temp_max":15.14,"pressure":1015,"sea_level":1015,"grnd_level":1007,"humidity":69,"temp_kf":0},"weather":[{"id":801,"main":"Clouds","description":"lleugerament ennuvolat","icon":"02d"}],"clouds":{"all":23},"wind":{"speed":5,"deg":195,"gust":6.13},"visibility":10000,"pop":0,"sys":{"pod":"d"},"dt_txt":"2026-03-13 15:00:00"},{"dt":1773424800,"main":{"temp":13.93,"feels_like":13.47,"temp_min":13.93,"temp_max":13.93,"pressure":1012,"sea_level":1012,"grnd_level":1005,"humidity":80,"temp_kf":0},"weather":[{"id":801,"main":"Clouds","description":"lleugerament ennuvolat","icon":"02n"}],"clouds":{"all":12},"wind":{"speed":3.12,"deg":200,"gust":5.12},"visibility":10000,"pop":0,"sys":{"pod":"n"},"dt_txt":"2026-03-13 18:00:00"},{"dt":1773435600,"main":{"temp":13.5,"feels_like":13.07,"temp_min":13.5,"temp_max":13.5,"pressure":1011,"sea_level":1011,"grnd_level":1003,"humidity":83,"temp_kf":0},"weather":[{"id":804,"main":"Clouds","description":"ennuvolat","icon":"04n"}],"clouds":{"all":90},"wind":{"speed":3.09,"deg":225,"gust":6.32},"visibility":10000,"pop":0,"sys":{"pod":"n"},"dt_txt":"2026-03-13 21:00:00"},{"dt":1773446400,"main":{"temp":13.44,"feels_like":12.93,"temp_min":13.44,"temp_max":13.44,"pressure":1007,"sea_level":1007,"grnd_level":999,"humidity":80,"temp_kf":0},"weather":[{"id":804,"main":"Clouds","description":"ennuvolat","icon":"04n"}],"clouds":{"all":95},"wind":{"speed":3.53,"deg":237,"gust":5.87},"visibility":10000,"pop":0,"sys":{"pod":"n"},"dt_txt":"2026-03-14 00:00:00"},{"dt":1773457200,"main":{"temp":13.02,"feels_like":12.54,"temp_min":13.02,"temp_max":13.02,"pressure":1004,"sea_level":1004,"grnd_level":996,"humidity":83,"temp_kf":0},"weather":[{"id":804,"main":"Clouds","description":"ennuvolat","icon":"04n"}],"clouds":{"all":100},"wind":{"speed":2.52,"deg":239,"gust":3.08},"visibility":10000,"pop":0,"sys":{"pod":"n"},"dt_txt":"2026-03-14 03:00:00"},{"dt":1773468000,"main":{"temp":12.51,"feels_like":11.96,"temp_min":12.51,"temp_max":12.51,"pressure":1003,"sea_level":1003,"grnd_level":995,"humidity":82,"temp_kf":0},"weather":[{"id":500,"main":"Rain","description":"pluja suau","icon":"10n"}],"clouds":{"all":100},"wind":{"speed":1.56,"deg":223,"gust":4.45},"visibility":9775,"pop":1,"rain":{"3h":1.25},"sys":{"pod":"n"},"dt_txt":"2026-03-14 06:00:00"},{"dt":1773478800,"main":{"temp":9.08,"feels_like":5.37,"temp_min":9.08,"temp_max":9.08,"pressure":1003,"sea_level":1003,"grnd_level":995,"humidity":90,"temp_kf":0},"weather":[{"id":501,"main":"Rain","description":"pluja","icon":"10d"}],"clouds":{"all":100},"wind":{"speed":8.42,"deg":73,"gust":10.91},"visibility":4946,"pop":1,"rain":{"3h":6.72},"sys":{"pod":"d"},"dt_txt":"2026-03-14 09:00:00"},{"dt":1773489600,"main":{"temp":7.88,"feels_like":5.72,"temp_min":7.88,"temp_max":7.88,"pressure":1005,"sea_level":1005,"grnd_level":997,"humidity":84,"temp_kf":0},"weather":[{"id":501,"main":"Rain","description":"pluja","icon":"10d"}],"clouds":{"all":100},"wind":{"speed":3.4,"deg":28,"gust":3.97},"visibility":10000,"pop":1,"rain":{"3h":9},"sys":{"pod":"d"},"dt_txt":"2026-03-14 12:00:00"},{"dt":1773500400,"main":{"temp":6.76,"feels_like":4.57,"temp_min":6.76,"temp_max":6.76,"pressure":1005,"sea_level":1005,"grnd_level":997,"humidity":81,"temp_kf":0},"weather":[{"id":501,"main":"Rain","description":"pluja","icon":"10d"}],"clouds":{"all":100},"wind":{"speed":3.08,"deg":89,"gust":2.46},"visibility":10000,"pop":1,"rain":{"3h":3.39},"sys":{"pod":"d"},"dt_txt":"2026-03-14 15:00:00"},{"dt":1773511200,"main":{"temp":7.37,"feels_like":6.34,"temp_min":7.37,"temp_max":7.37,"pressure":1006,"sea_level":1006,"grnd_level":998,"humidity":73,"temp_kf":0},"weather":[{"id":804,"main":"Clouds","description":"ennuvolat","icon":"04n"}],"clouds":{"all":100},"wind":{"speed":1.78,"deg":210,"gust":2.42},"visibility":10000,"pop":0.8,"sys":{"pod":"n"},"dt_txt":"2026-03-14 18:00:00"},{"dt":1773522000,"main":{"temp":7.61,"feels_like":4.78,"temp_min":7.61,"temp_max":7.61,"pressure":1007,"sea_level":1007,"grnd_level":999,"humidity":83,"temp_kf":0},"weather":[{"id":500,"main":"Rain","description":"pluja suau","icon":"10n"}],"clouds":{"all":30},"wind":{"speed":4.59,"deg":281,"gust":6.85},"visibility":10000,"pop":0.2,"rain":{"3h":0.11},"sys":{"pod":"n"},"dt_txt":"2026-03-14 21:00:00"},{"dt":1773532800,"main":{"temp":7.05,"feels_like":5.63,"temp_min":7.05,"temp_max":7.05,"pressure":1007,"sea_level":1007,"grnd_level":999,"humidity":65,"temp_kf":0},"weather":[{"id":801,"main":"Clouds","description":"lleugerament ennuvolat","icon":"02n"}],"clouds":{"all":16},"wind":{"speed":2.14,"deg":329,"gust":1.87},"visibility":10000,"pop":0,"sys":{"pod":"n"},"dt_txt":"2026-03-15 00:00:00"},{"dt":1773543600,"main":{"temp":6.33,"feels_like":4.22,"temp_min":6.33,"temp_max":6.33,"pressure":1006,"sea_level":1006,"grnd_level":998,"humidity":59,"temp_kf":0},"weather":[{"id":800,"main":"Clear","description":"cel net","icon":"01n"}],"clouds":{"all":1},"wind":{"speed":2.84,"deg":305,"gust":6.55},"visibility":10000,"pop":0,"sys":{"pod":"n"},"dt_txt":"2026-03-15 03:00:00"},{"dt":1773554400,"main":{"temp":6.41,"feels_like":2.67,"temp_min":6.41,"temp_max":6.41,"pressure":1006,"sea_level":1006,"grnd_level":997,"humidity":56,"temp_kf":0},"weather":[{"id":800,"main":"Clear","description":"cel net","icon":"01n"}],"clouds":{"all":1},"wind":{"speed":6.03,"deg":295,"gust":11.61},"visibility":10000,"pop":0,"sys":{"pod":"n"},"dt_txt":"2026-03-15 06:00:00"},{"dt":1773565200,"main":{"temp":11.07,"feels_like":9.22,"temp_min":11.07,"temp_max":11.07,"pressure":1006,"sea_level":1006,"grnd_level":998,"humidity":38,"temp_kf":0},"weather":[{"id":800,"main":"Clear","description":"cel net","icon":"01d"}],"clouds":{"all":0},"wind":{"speed":6.62,"deg":299,"gust":6.48},"visibility":10000,"pop":0,"sys":{"pod":"d"},"dt_txt":"2026-03-15 09:00:00"},{"dt":1773576000,"main":{"temp":14.42,"feels_like":12.54,"temp_min":14.42,"temp_max":14.42,"pressure":1006,"sea_level":1006,"grnd_level":998,"humidity":24,"temp_kf":0},"weather":[{"id":802,"main":"Clouds","description":"núvols dispersos","icon":"03d"}],"clouds":{"all":31},"wind":{"speed":6.89,"deg":313,"gust":6.95},"visibility":10000,"pop":0,"sys":{"pod":"d"},"dt_txt":"2026-03-15 12:00:00"},{"dt":1773586800,"main":{"temp":15.78,"feels_like":14.17,"temp_min":15.78,"temp_max":15.78,"pressure":1006,"sea_level":1006,"grnd_level":998,"humidity":29,"temp_kf":0},"weather":[{"id":803,"main":"Clouds","description":"nuvolositat variable","icon":"04d"}],"clouds":{"all":66},"wind":{"speed":2.88,"deg":307,"gust":3.57},"visibility":10000,"pop":0,"sys":{"pod":"d"},"dt_txt":"2026-03-15 15:00:00"},{"dt":1773597600,"main":{"temp":13.85,"feels_like":12.31,"temp_min":13.85,"temp_max":13.85,"pressure":1009,"sea_level":1009,"grnd_level":1001,"humidity":39,"temp_kf":0},"weather":[{"id":803,"main":"Clouds","description":"nuvolositat variable","icon":"04n"}],"clouds":{"all":79},"wind":{"speed":1.34,"deg":227,"gust":3.56},"visibility":10000,"pop":0,"sys":{"pod":"n"},"dt_txt":"2026-03-15 18:00:00"},{"dt":1773608400,"main":{"temp":11.37,"feels_like":9.69,"temp_min":11.37,"temp_max":11.37,"pressure":1013,"sea_level":1013,"grnd_level":1005,"humidity":43,"temp_kf":0},"weather":[{"id":803,"main":"Clouds","description":"nuvolositat variable","icon":"04n"}],"clouds":{"all":64},"wind":{"speed":2.59,"deg":310,"gust":3.35},"visibility":10000,"pop":0,"sys":{"pod":"n"},"dt_txt":"2026-03-15 21:00:00"},{"dt":1773619200,"main":{"temp":9.26,"feels_like":7.58,"temp_min":9.26,"temp_max":9.26,"pressure":1014,"sea_level":1014,"grnd_level":1006,"humidity":41,"temp_kf":0},"weather":[{"id":802,"main":"Clouds","description":"núvols dispersos","icon":"03n"}],"clouds":{"all":49},"wind":{"speed":3.07,"deg":329,"gust":3.86},"visibility":10000,"pop":0,"sys":{"pod":"n"},"dt_txt":"2026-03-16 00:00:00"},{"dt":1773630000,"main":{"temp":7.98,"feels_like":6.43,"temp_min":7.98,"temp_max":7.98,"pressure":1015,"sea_level":1015,"grnd_level":1007,"humidity":38,"temp_kf":0},"weather":[{"id":800,"main":"Clear","description":"cel net","icon":"01n"}],"clouds":{"all":0},"wind":{"speed":2.5,"deg":317,"gust":2.81},"visibility":10000,"pop":0,"sys":{"pod":"n"},"dt_txt":"2026-03-16 03:00:00"},{"dt":1773640800,"main":{"temp":7.01,"feels_like":4.95,"temp_min":7.01,"temp_max":7.01,"pressure":1016,"sea_level":1016,"grnd_level":1008,"humidity":38,"temp_kf":0},"weather":[{"id":800,"main":"Clear","description":"cel net","icon":"01n"}],"clouds":{"all":0},"wind":{"speed":2.96,"deg":301,"gust":3.15},"visibility":10000,"pop":0,"sys":{"pod":"n"},"dt_txt":"2026-03-16 06:00:00"}],"city":{"id":6356147,"name":"Masnou, El","coord":{"lat":41.4853,"lon":2.3275},"country":"ES","population":22288,"timezone":3600,"sunrise":1773209381,"sunset":1773251522}}