{"cod":"200","message":0,"cnt":40,"list":[{"dt":1778068800,"main":{"temp":18.93,"feels_like":18.37,"temp_min":18.93,"temp_max":19.1,"pressure":1012,"sea_level":1012,"grnd_level":1005,"humidity":57,"temp_kf":-0.17},"weather":[{"id":500,"main":"Rain","description":"pluja suau","icon":"10d"}],"clouds":{"all":16},"wind":{"speed":5.36,"deg":140,"gust":4.45},"visibility":10000,"pop":0.26,"rain":{"3h":0.54},"sys":{"pod":"d"},"dt_txt":"2026-05-06 12:00:00"},{"dt":1778079600,"main":{"temp":19.33,"feels_like":18.99,"temp_min":19.33,"temp_max":19.58,"pressure":1012,"sea_level":1012,"grnd_level":1004,"humidity":64,"temp_kf":-0.25},"weather":[{"id":500,"main":"Rain","description":"pluja suau","icon":"10d"}],"clouds":{"all":15},"wind":{"speed":4.64,"deg":148,"gust":4.3},"visibility":10000,"pop":0.66,"rain":{"3h":0.41},"sys":{"pod":"d"},"dt_txt":"2026-05-06 15:00:00"},{"dt":1778090400,"main":{"temp":17.18,"feels_like":16.81,"temp_min":17.18,"temp_max":17.18,"pressure":1012,"sea_level":1012,"grnd_level":1004,"humidity":71,"temp_kf":0},"weather":[{"id":500,"main":"Rain","description":"pluja suau","icon":"10d"}],"clouds":{"all":24},"wind":{"speed":3.48,"deg":133,"gust":3.19},"visibility":10000,"pop":0.43,"rain":{"3h":0.12},"sys":{"pod":"d"},"dt_txt":"2026-05-06 18:00:00"},{"dt":1778101200,"main":{"temp":15.16,"feels_like":14.79,"temp_min":15.16,"temp_max":15.16,"pressure":1014,"sea_level":1014,"grnd_level":1006,"humidity":79,"temp_kf":0},"weather":[{"id":802,"main":"Clouds","description":"núvols dispersos","icon":"03n"}],"clouds":{"all":32},"wind":{"speed":2.34,"deg":95,"gust":2.81},"visibility":10000,"pop":0,"sys":{"pod":"n"},"dt_txt":"2026-05-06 21:00:00"},{"dt":1778112000,"main":{"temp":14.83,"feels_like":14.38,"temp_min":14.83,"temp_max":14.83,"pressure":1014,"sea_level":1014,"grnd_level":1006,"humidity":77,"temp_kf":0},"weather":[{"id":803,"main":"Clouds","description":"nuvolositat variable","icon":"04n"}],"clouds":{"all":65},"wind":{"speed":2.9,"deg":49,"gust":3.45},"visibility":10000,"pop":0,"sys":{"pod":"n"},"dt_txt":"2026-05-07 00:00:00"},{"dt":1778122800,"main":{"temp":14.25,"feels_like":13.69,"temp_min":14.25,"temp_max":14.25,"pressure":1013,"sea_level":1013,"grnd_level":1005,"humidity":75,"temp_kf":0},"weather":[{"id":804,"main":"Clouds","description":"ennuvolat","icon":"04n"}],"clouds":{"all":100},"wind":{"speed":2.68,"deg":41,"gust":2.97},"visibility":10000,"pop":0,"sys":{"pod":"n"},"dt_txt":"2026-05-07 03:00:00"},{"dt":1778133600,"main":{"temp":14.41,"feels_like":13.84,"temp_min":14.41,"temp_max":14.41,"pressure":1014,"sea_level":1014,"grnd_level":1006,"humidity":74,"temp_kf":0},"weather":[{"id":804,"main":"Clouds","description":"ennuvolat","icon":"04d"}],"clouds":{"all":99},"wind":{"speed":2.85,"deg":54,"gust":3.31},"visibility":10000,"pop":0,"sys":{"pod":"d"},"dt_txt":"2026-05-07 06:00:00"},{"dt":1778144400,"main":{"temp":16.79,"feels_like":16.33,"temp_min":16.79,"temp_max":16.79,"pressure":1014,"sea_level":1014,"grnd_level":1006,"humidity":69,"temp_kf":0},"weather":[{"id":802,"main":"Clouds","description":"núvols dispersos","icon":"03d"}],"clouds":{"all":38},"wind":{"speed":4.3,"deg":94,"gust":4.37},"visibility":10000,"pop":0,"sys":{"pod":"d"},"dt_txt":"2026-05-07 09:00:00"},{"dt":1778155200,"main":{"temp":17.39,"feels_like":16.93,"temp_min":17.39,"temp_max":17.39,"pressure":1013,"sea_level":1013,"grnd_level":1006,"humidity":67,"temp_kf":0},"weather":[{"id":803,"main":"Clouds","description":"nuvolositat variable","icon":"04d"}],"clouds":{"all":51},"wind":{"speed":5.22,"deg":109,"gust":4.82},"visibility":10000,"pop":0,"sys":{"pod":"d"},"dt_txt":"2026-05-07 12:00:00"},{"dt":1778166000,"main":{"temp":17.19,"feels_like":16.69,"temp_min":17.19,"temp_max":17.19,"pressure":1012,"sea_level":1012,"grnd_level":1004,"humidity":66,"temp_kf":0},"weather":[{"id":804,"main":"Clouds","description":"ennuvolat","icon":"04d"}],"clouds":{"all":100},"wind":{"speed":4.84,"deg":110,"gust":4.58},"visibility":10000,"pop":0,"sys":{"pod":"d"},"dt_txt":"2026-05-07 15:00:00"},{"dt":1778176800,"main":{"temp":16.31,"feels_like":15.82,"temp_min":16.31,"temp_max":16.31,"pressure":1012,"sea_level":1012,"grnd_level":1004,"humidity":70,"temp_kf":0},"weather":[{"id":804,"main":"Clouds","description":"ennuvolat","icon":"04d"}],"clouds":{"all":100},"wind":{"speed":3.02,"deg":95,"gust":3.74},"visibility":10000,"pop":0,"sys":{"pod":"d"},"dt_txt":"2026-05-07 18:00:00"},{"dt":1778187600,"main":{"temp":15.83,"feels_like":15.37,"temp_min":15.83,"temp_max":15.83,"pressure":1014,"sea_level":1014,"grnd_level":1006,"humidity":73,"temp_kf":0},"weather":[{"id":804,"main":"Clouds","description":"ennuvolat","icon":"04n"}],"clouds":{"all":100},"wind":{"speed":2.74,"deg":53,"gust":2.97},"visibility":10000,"pop":0,"sys":{"pod":"n"},"dt_txt":"2026-05-07 21:00:00"},{"dt":1778198400,"main":{"temp":15.39,"feels_like":14.71,"temp_min":15.39,"temp_max":15.39,"pressure":1013,"sea_level":1013,"grnd_level":1005,"humidity":66,"temp_kf":0},"weather":[{"id":804,"main":"Clouds","description":"ennuvolat","icon":"04n"}],"clouds":{"all":100},"wind":{"speed":1.41,"deg":28,"gust":1.66},"visibility":10000,"pop":0,"sys":{"pod":"n"},"dt_txt":"2026-05-08 00:00:00"},{"dt":1778209200,"main":{"temp":14.64,"feels_like":13.94,"temp_min":14.64,"temp_max":14.64,"pressure":1013,"sea_level":1013,"grnd_level":1005,"humidity":68,"temp_kf":0},"weather":[{"id":802,"main":"Clouds","description":"núvols dispersos","icon":"03n"}],"clouds":{"all":45},"wind":{"speed":1.02,"deg":115,"gust":0.93},"visibility":10000,"pop":0,"sys":{"pod":"n"},"dt_txt":"2026-05-08 03:00:00"},{"dt":1778220000,"main":{"temp":14.88,"feels_like":14.3,"temp_min":14.88,"temp_max":14.88,"pressure":1014,"sea_level":1014,"grnd_level":1006,"humidity":72,"temp_kf":0},"weather":[{"id":802,"main":"Clouds","description":"núvols dispersos","icon":"03d"}],"clouds":{"all":30},"wind":{"speed":2.11,"deg":44,"gust":2.08},"visibility":10000,"pop":0,"sys":{"pod":"d"},"dt_txt":"2026-05-08 06:00:00"},{"dt":1778230800,"main":{"temp":17.26,"feels_like":16.63,"temp_min":17.26,"temp_max":17.26,"pressure":1015,"sea_level":1015,"grnd_level":1007,"humidity":61,"temp_kf":0},"weather":[{"id":804,"main":"Clouds","description":"ennuvolat","icon":"04d"}],"clouds":{"all":96},"wind":{"speed":2.15,"deg":160,"gust":2.04},"visibility":10000,"pop":0,"sys":{"pod":"d"},"dt_txt":"2026-05-08 09:00:00"},{"dt":1778241600,"main":{"temp":17.48,"feels_like":16.85,"temp_min":17.48,"temp_max":17.48,"pressure":1015,"sea_level":1015,"grnd_level":1007,"humidity":60,"temp_kf":0},"weather":[{"id":804,"main":"Clouds","description":"ennuvolat","icon":"04d"}],"clouds":{"all":98},"wind":{"speed":3.52,"deg":171,"gust":3.33},"visibility":10000,"pop":0,"sys":{"pod":"d"},"dt_txt":"2026-05-08 12:00:00"},{"dt":1778252400,"main":{"temp":17.61,"feels_like":17.12,"temp_min":17.61,"temp_max":17.61,"pressure":1014,"sea_level":1014,"grnd_level":1006,"humidity":65,"temp_kf":0},"weather":[{"id":804,"main":"Clouds","description":"ennuvolat","icon":"04d"}],"clouds":{"all":100},"wind":{"speed":3.33,"deg":191,"gust":3.53},"visibility":10000,"pop":0,"sys":{"pod":"d"},"dt_txt":"2026-05-08 15:00:00"},{"dt":1778263200,"main":{"temp":17.57,"feels_like":17.21,"temp_min":17.57,"temp_max":17.57,"pressure":1014,"sea_level":1014,"grnd_level":1006,"humidity":70,"temp_kf":0},"weather":[{"id":803,"main":"Clouds","description":"nuvolositat variable","icon":"04d"}],"clouds":{"all":60},"wind":{"speed":2.57,"deg":165,"gust":2.81},"visibility":10000,"pop":0,"sys":{"pod":"d"},"dt_txt":"2026-05-08 18:00:00"},{"dt":1778274000,"main":{"temp":16.39,"feels_like":16.15,"temp_min":16.39,"temp_max":16.39,"pressure":1016,"sea_level":1016,"grnd_level":1008,"humidity":79,"temp_kf":0},"weather":[{"id":800,"main":"Clear","description":"cel net","icon":"01n"}],"clouds":{"all":4},"wind":{"speed":1.46,"deg":162,"gust":2.18},"visibility":10000,"pop":0,"sys":{"pod":"n"},"dt_txt":"2026-05-08 21:00:00"},{"dt":1778284800,"main":{"temp":15.74,"feels_like":15.48,"temp_min":15.74,"temp_max":15.74,"pressure":1015,"sea_level":1015,"grnd_level":1007,"humidity":81,"temp_kf":0},"weather":[{"id":801,"main":"Clouds","description":"lleugerament ennuvolat","icon":"02n"}],"clouds":{"all":12},"wind":{"speed":0.68,"deg":50,"gust":0.66},"visibility":10000,"pop":0,"sys":{"pod":"n"},"dt_txt":"2026-05-09 00:00:00"},{"dt":1778295600,"main":{"temp":14.91,"feels_like":14.62,"temp_min":14.91,"temp_max":14.91,"pressure":1014,"sea_level":1014,"grnd_level":1006,"humidity":83,"temp_kf":0},"weather":[{"id":803,"main":"Clouds","description":"nuvolositat variable","icon":"04n"}],"clouds":{"all":64},"wind":{"speed":1.69,"deg":41,"gust":1.64},"visibility":10000,"pop":0,"sys":{"pod":"n"},"dt_txt":"2026-05-09 03:00:00"},{"dt":1778306400,"main":{"temp":14.98,"feels_like":14.6,"temp_min":14.98,"temp_max":14.98,"pressure":1014,"sea_level":1014,"grnd_level":1006,"humidity":79,"temp_kf":0},"weather":[{"id":803,"main":"Clouds","description":"nuvolositat variable","icon":"04d"}],"clouds":{"all":82},"wind":{"speed":3.08,"deg":54,"gust":3.71},"visibility":10000,"pop":0,"sys":{"pod":"d"},"dt_txt":"2026-05-09 06:00:00"},{"dt":1778317200,"main":{"temp":17.84,"feels_like":17.38,"temp_min":17.84,"temp_max":17.84,"pressure":1014,"sea_level":1014,"grnd_level":1006,"humidity":65,"temp_kf":0},"weather":[{"id":804,"main":"Clouds","description":"ennuvolat","icon":"04d"}],"clouds":{"all":100},"wind":{"speed":5.58,"deg":80,"gust":7.01},"visibility":10000,"pop":0,"sys":{"pod":"d"},"dt_txt":"2026-05-09 09:00:00"},{"dt":1778328000,"main":{"temp":18.56,"feels_like":18.14,"temp_min":18.56,"temp_max":18.56,"pressure":1012,"sea_level":1012,"grnd_level":1005,"humidity":64,"temp_kf":0},"weather":[{"id":804,"main":"Clouds","description":"ennuvolat","icon":"04d"}],"clouds":{"all":100},"wind":{"speed":7.08,"deg":92,"gust":8.96},"visibility":10000,"pop":0,"sys":{"pod":"d"},"dt_txt":"2026-05-09 12:00:00"},{"dt":1778338800,"main":{"temp":17.77,"feels_like":17.4,"temp_min":17.77,"temp_max":17.77,"pressure":1011,"sea_level":1011,"grnd_level":1003,"humidity":69,"temp_kf":0},"weather":[{"id":500,"main":"Rain","description":"pluja suau","icon":"10d"}],"clouds":{"all":100},"wind":{"speed":5.78,"deg":74,"gust":7.69},"visibility":10000,"pop":0.21,"rain":{"3h":0.13},"sys":{"pod":"d"},"dt_txt":"2026-05-09 15:00:00"},{"dt":1778349600,"main":{"temp":16.54,"feels_like":16.16,"temp_min":16.54,"temp_max":16.54,"pressure":1012,"sea_level":1012,"grnd_level":1004,"humidity":73,"temp_kf":0},"weather":[{"id":500,"main":"Rain","description":"pluja suau","icon":"10d"}],"clouds":{"all":100},"wind":{"speed":2.39,"deg":73,"gust":3.9},"visibility":10000,"pop":0.35,"rain":{"3h":0.34},"sys":{"pod":"d"},"dt_txt":"2026-05-09 18:00:00"},{"dt":1778360400,"main":{"temp":17.01,"feels_like":16.57,"temp_min":17.01,"temp_max":17.01,"pressure":1013,"sea_level":1013,"grnd_level":1005,"humidity":69,"temp_kf":0},"weather":[{"id":804,"main":"Clouds","description":"ennuvolat","icon":"04n"}],"clouds":{"all":99},"wind":{"speed":0.65,"deg":251,"gust":1.53},"visibility":10000,"pop":0,"sys":{"pod":"n"},"dt_txt":"2026-05-09 21:00:00"},{"dt":1778371200,"main":{"temp":16.95,"feels_like":16.58,"temp_min":16.95,"temp_max":16.95,"pressure":1012,"sea_level":1012,"grnd_level":1004,"humidity":72,"temp_kf":0},"weather":[{"id":804,"main":"Clouds","description":"ennuvolat","icon":"04n"}],"clouds":{"all":96},"wind":{"speed":3.2,"deg":239,"gust":4.68},"visibility":10000,"pop":0,"sys":{"pod":"n"},"dt_txt":"2026-05-10 00:00:00"},{"dt":1778382000,"main":{"temp":15.77,"feels_like":15.47,"temp_min":15.77,"temp_max":15.77,"pressure":1011,"sea_level":1011,"grnd_level":1003,"humidity":79,"temp_kf":0},"weather":[{"id":800,"main":"Clear","description":"cel net","icon":"01n"}],"clouds":{"all":0},"wind":{"speed":3.36,"deg":264,"gust":5},"visibility":10000,"pop":0,"sys":{"pod":"n"},"dt_txt":"2026-05-10 03:00:00"},{"dt":1778392800,"main":{"temp":16.04,"feels_like":15.58,"temp_min":16.04,"temp_max":16.04,"pressure":1011,"sea_level":1011,"grnd_level":1003,"humidity":72,"temp_kf":0},"weather":[{"id":800,"main":"Clear","description":"cel net","icon":"01d"}],"clouds":{"all":4},"wind":{"speed":3.5,"deg":262,"gust":5.9},"visibility":10000,"pop":0,"sys":{"pod":"d"},"dt_txt":"2026-05-10 06:00:00"},{"dt":1778403600,"main":{"temp":20.04,"feels_like":19.48,"temp_min":20.04,"temp_max":20.04,"pressure":1011,"sea_level":1011,"grnd_level":1003,"humidity":53,"temp_kf":0},"weather":[{"id":804,"main":"Clouds","description":"ennuvolat","icon":"04d"}],"clouds":{"all":100},"wind":{"speed":5.57,"deg":251,"gust":8.18},"visibility":10000,"pop":0,"sys":{"pod":"d"},"dt_txt":"2026-05-10 09:00:00"},{"dt":1778414400,"main":{"temp":21.51,"feels_like":20.97,"temp_min":21.51,"temp_max":21.51,"pressure":1010,"sea_level":1010,"grnd_level":1002,"humidity":48,"temp_kf":0},"weather":[{"id":804,"main":"Clouds","description":"ennuvolat","icon":"04d"}],"clouds":{"all":100},"wind":{"speed":8.05,"deg":232,"gust":11.81},"visibility":10000,"pop":0,"sys":{"pod":"d"},"dt_txt":"2026-05-10 12:00:00"},{"dt":1778425200,"main":{"temp":20.86,"feels_like":20.28,"temp_min":20.86,"temp_max":20.86,"pressure":1009,"sea_level":1009,"grnd_level":1002,"humidity":49,"temp_kf":0},"weather":[{"id":804,"main":"Clouds","description":"ennuvolat","icon":"04d"}],"clouds":{"all":94},"wind":{"speed":7.46,"deg":271,"gust":10.83},"visibility":10000,"pop":0,"sys":{"pod":"d"},"dt_txt":"2026-05-10 15:00:00"},{"dt":1778436000,"main":{"temp":20.89,"feels_like":20.39,"temp_min":20.89,"temp_max":20.89,"pressure":1009,"sea_level":1009,"grnd_level":1001,"humidity":52,"temp_kf":0},"weather":[{"id":803,"main":"Clouds","description":"nuvolositat variable","icon":"04d"}],"clouds":{"all":73},"wind":{"speed":6.99,"deg":226,"gust":11.29},"visibility":10000,"pop":0,"sys":{"pod":"d"},"dt_txt":"2026-05-10 18:00:00"},{"dt":1778446800,"main":{"temp":19.19,"feels_like":18.84,"temp_min":19.19,"temp_max":19.19,"pressure":1010,"sea_level":1010,"grnd_level":1003,"humidity":64,"temp_kf":0},"weather":[{"id":800,"main":"Clear","description":"cel net","icon":"01n"}],"clouds":{"all":7},"wind":{"speed":4.57,"deg":242,"gust":8.18},"visibility":10000,"pop":0,"sys":{"pod":"n"},"dt_txt":"2026-05-10 21:00:00"},{"dt":1778457600,"main":{"temp":17.85,"feels_like":17.54,"temp_min":17.85,"temp_max":17.85,"pressure":1011,"sea_level":1011,"grnd_level":1003,"humidity":71,"temp_kf":0},"weather":[{"id":800,"main":"Clear","description":"cel net","icon":"01n"}],"clouds":{"all":3},"wind":{"speed":1.76,"deg":268,"gust":2.2},"visibility":10000,"pop":0,"sys":{"pod":"n"},"dt_txt":"2026-05-11 00:00:00"},{"dt":1778468400,"main":{"temp":16.89,"feels_like":16.18,"temp_min":16.89,"temp_max":16.89,"pressure":1010,"sea_level":1010,"grnd_level":1002,"humidity":59,"temp_kf":0},"weather":[{"id":803,"main":"Clouds","description":"nuvolositat variable","icon":"04n"}],"clouds":{"all":69},"wind":{"speed":1.69,"deg":310,"gust":1.8},"visibility":10000,"pop":0,"sys":{"pod":"n"},"dt_txt":"2026-05-11 03:00:00"},{"dt":1778479200,"main":{"temp":17,"feels_like":16.17,"temp_min":17,"temp_max":17,"pressure":1011,"sea_level":1011,"grnd_level":1003,"humidity":54,"temp_kf":0},"weather":[{"id":803,"main":"Clouds","description":"nuvolositat variable","icon":"04d"}],"clouds":{"all":59},"wind":{"speed":1.27,"deg":296,"gust":1.61},"visibility":10000,"pop":0,"sys":{"pod":"d"},"dt_txt":"2026-05-11 06:00:00"},{"dt":1778490000,"main":{"temp":21.03,"feels_like":20.23,"temp_min":21.03,"temp_max":21.03,"pressure":1010,"sea_level":1010,"grnd_level":1002,"humidity":40,"temp_kf":0},"weather":[{"id":800,"main":"Clear","description":"cel net","icon":"01d"}],"clouds":{"all":9},"wind":{"speed":3.21,"deg":229,"gust":4.75},"visibility":10000,"pop":0,"sys":{"pod":"d"},"dt_txt":"2026-05-11 09:00:00"}],"city":{"id":6356147,"name":"Masnou, El","coord":{"lat":41.4853,"lon":2.3275},"country":"ES","population":22288,"timezone":7200,"sunrise":1778042502,"sunset":1778093573}}