{
  "zona": "Maresme central",
  "data": "29/03/2026 09:04",
  "indexTotal": 19,
  "risc": "baix",
  "dominant": {
    "nom": "Plàtan",
    "text": "Predomini de plàtan segons condicions locals."
  },
  "comentari": "Model automàtic basat en meteorologia local i temporada.",
  "tipus": [
    {
      "nom": "Plàtan",
      "valor": 39
    },
    {
      "nom": "Cupressàcies",
      "valor": 22
    },
    {
      "nom": "Parietària",
      "valor": 27
    },
    {
      "nom": "Pi",
      "valor": 19
    },
    {
      "nom": "Gramínies",
      "valor": 9
    },
    {
      "nom": "Olivera",
      "valor": 2
    }
  ],
  "historic": [],
  "previsio": [
    {
      "dia": "Demà",
      "index": 10,
      "risc": "baix"
    },
    {
      "dia": "Demà passat",
      "index": 6,
      "risc": "baix"
    }
  ]
}