{
  "zona": "Maresme central",
  "data": "29/03/2026 18:04",
  "indexTotal": 33,
  "risc": "moderat",
  "dominant": {
    "nom": "Plàtan",
    "text": "Predomini de plàtan segons condicions locals."
  },
  "comentari": "Model automàtic basat en meteorologia local i temporada.",
  "tipus": [
    {
      "nom": "Plàtan",
      "valor": 62
    },
    {
      "nom": "Cupressàcies",
      "valor": 35
    },
    {
      "nom": "Parietària",
      "valor": 49
    },
    {
      "nom": "Pi",
      "valor": 34
    },
    {
      "nom": "Gramínies",
      "valor": 15
    },
    {
      "nom": "Olivera",
      "valor": 3
    }
  ],
  "historic": [],
  "previsio": [
    {
      "dia": "Demà",
      "index": 33,
      "risc": "moderat"
    },
    {
      "dia": "Demà passat",
      "index": 33,
      "risc": "moderat"
    }
  ]
}